Workbook

Sheet COVER
B2: APEX RAINIER — VALIDATION & TEST WORKBOOK
B3: Manual validation against a ground truth · QA sign-off workbook · English edition, August 2026
B5: Run identification
B6: App commit (git rev-parse --short HEAD)
B7: Site / edition | C7: Main repo (NLX1) · Winterswijk (NLK1) · Ankerkade (NLU1)
B8: Ground-truth ID(s) (see GT Register)
B9: Planning month · actuals months
B10: Validator
B11: Developer
B12: Reviewer
B13: Date started · date finished
B14: Evidence folder | C14: validatie\<yyyy-mm-dd>_<commit>_<GT-ID>\ (outside the repository)
B16: How to use this workbook
B17: 1. Freeze the ground truth first (GT Register): the client Excel after a full macro run, hashed with SHA-256. Without a GT-ID there is no validation round.
B18: 2. Run the round in order R0 → R7 (see the strategy document docs/validatiestrategie.md). Sheets are named after the step they belong to.
B19: 3. Yellow cells are inputs for the tester. White cells with formulas (Δ, match, counts) compute themselves.
B20: 4. Every check gets a Status: PASS / FAIL / BLOCKED / N/A (TODO = not yet executed). Every FAIL gets a row in the Deviation Register with a class A–F and a decision.
B21: 5. Tolerances: volumes/hours exact (abs 1e-6 or rel 1e-9), money 0.01, FTE 0.001. Never widen a tolerance to make a round pass — document instead.
B22: 6. Evidence: screenshot or export file name per check, stored in the evidence folder. Screenshots of Excel must show the formula bar (see docs/screenshot-richtlijnen.md).
B23: 7. Tool: python tools/ground_truth_diff.py <GT>.xlsm <export>.xlsx --md report.md --out deviations.xlsx (exit 0 = all within tolerance).
B25: Pass criteria for release
B26: ✔ Baseline parity (R1) on ≥ 1 GT-A per site: 0 open class-A findings; all other cells Δ=0 or covered by an erratum (B) or a taken decision (C).
B27: ✔ Calculation chains (R2): five chains K1–K5 filled in; hand value = app value = Excel value, or the difference is classified and decided.
B28: ✔ Invariants (R4): I1–I11 without open deviations.
... B32: Status summary (live)
B33: Sheet | C33: Checks | D33: PASS | E33: FAIL | F33: BLOCKED | G33: N/A | H33: TODO
B34: R1 Baseline Parity | C34: =COUNTA('R1 Baseline Parity'!N5:N20)-COUNTIF('R1 Baseline Parity'!N5:N20,"") | D34: =COUNTIF('R1 Baseline Parity'!N5:N20,"PASS") | E34: =COUNTIF('R1 Baseline Parity'!N5:N20,"FAIL") | F34: =COUNTIF('R1 Baseline Parity'!N5:N20,"BLOCKED") | G34: =COUNTIF('R1 Baseline Parity'!N5:N20,"N/A") | H34: =COUNTIF('R1 Baseline Parity'!N5:N20,"TODO")
B35: R2 Calc Chains | C35: =COUNTA('R2 Calc Chains'!K5:K63)-COUNTIF('R2 Calc Chains'!K5:K63,"") | D35: =COUNTIF('R2 Calc Chains'!K5:K63,"PASS") | E35: =COUNTIF('R2 Calc Chains'!K5:K63,"FAIL") | F35: =COUNTIF('R2 Calc Chains'!K5:K63,"BLOCKED") | G35: =COUNTIF('R2 Calc Chains'!K5:K63,"N/A") | H35: =COUNTIF('R2 Calc Chains'!K5:K63,"TODO")
B36: R4 Invariants | C36: =COUNTA('R4 Invariants'!I5:I38)-COUNTIF('R4 Invariants'!I5:I38,"") | D36: =COUNTIF('R4 Invariants'!I5:I38,"PASS") | E36: =COUNTIF('R4 Invariants'!I5:I38,"FAIL") | F36: =COUNTIF('R4 Invariants'!I5:I38,"BLOCKED") | G36: =COUNTIF('R4 Invariants'!I5:I38,"N/A") | H36: =COUNTIF('R4 Invariants'!I5:I38,"TODO")
B37: R3 Mirror Edits | C37: =COUNTA('R3 Mirror Edits'!L5:L17)-COUNTIF('R3 Mirror Edits'!L5:L17,"") | D37: =COUNTIF('R3 Mirror Edits'!L5:L17,"PASS") | E37: =COUNTIF('R3 Mirror Edits'!L5:L17,"FAIL") | F37: =COUNTIF('R3 Mirror Edits'!L5:L17,"BLOCKED") | G37: =COUNTIF('R3 Mirror Edits'!L5:L17,"N/A") | H37: =COUNTIF('R3 Mirror Edits'!L5:L17,"TODO")
B38: Functional Checks A-I | C38: =COUNTA('Functional Checks A-I'!G5:G142)-COUNTIF('Functional Checks A-I'!G5:G142,"") | D38: =COUNTIF('Functional Checks A-I'!G5:G142,"PASS") | E38: =COUNTIF('Functional Checks A-I'!G5:G142,"FAIL") | F38: =COUNTIF('Functional Checks A-I'!G5:G142,"BLOCKED") | G38: =COUNTIF('Functional Checks A-I'!G5:G142,"N/A") | H38: =COUNTIF('Functional Checks A-I'!G5:G142,"TODO")
B39: Engine Checks | C39: =COUNTA('Engine Checks'!F5:F143)-COUNTIF('Engine Checks'!F5:F143,"") | D39: =COUNTIF('Engine Checks'!F5:F143,"PASS") | E39: =COUNTIF('Engine Checks'!F5:F143,"FAIL") | F39: =COUNTIF('Engine Checks'!F5:F143,"BLOCKED") | G39: =COUNTIF('Engine Checks'!F5:F143,"N/A") | H39: =COUNTIF('Engine Checks'!F5:F143,"TODO")
B40: Scenario Sessions | C40: =COUNTA('Scenario Sessions'!F5:F75)-COUNTIF('Scenario Sessions'!F5:F75,"") | D40: =COUNTIF('Scenario Sessions'!F5:F75,"PASS") | E40: =COUNTIF('Scenario Sessions'!F5:F75,"FAIL") | F40: =COUNTIF('Scenario Sessions'!F5:F75,"BLOCKED") | G40: =COUNTIF('Scenario Sessions'!F5:F75,"N/A") | H40: =COUNTIF('Scenario Sessions'!F5:F75,"TODO")
B41: Human Tests A-K | C41: =COUNTA('Human Tests A-K'!G5:G130)-COUNTIF('Human Tests A-K'!G5:G130,"") | D41: =COUNTIF('Human Tests A-K'!G5:G130,"PASS") | E41: =COUNTIF('Human Tests A-K'!G5:G130,"FAIL") | F41: =COUNTIF('Human Tests A-K'!G5:G130,"BLOCKED") | G41: =COUNTIF('Human Tests A-K'!G5:G130,"N/A") | H41: =COUNTIF('Human Tests A-K'!G5:G130,"TODO")
B42: TOTAL | C42: =SUM(C34:C41) | D42: =SUM(D34:D41) | E42: =SUM(E34:E41) | F42: =SUM(F34:F41) | G42: =SUM(G34:G41) | H42: =SUM(H34:H41)
B46: Status legend
B47: PASS | C47: Check executed, result as expected (within tolerance).
B48: FAIL | C48: Deviation found → register it in the Deviation Register with class A–F.
B49: BLOCKED | C49: Could not be executed (missing input, prerequisite failed). Explain in Notes.
B50: N/A | C50: Not applicable for this site/round. Explain in Notes.
B51: TODO | C51: Not executed yet.
B53: Deviation classes
B54: A · App defect | C54: App deviates from the GT and the GT is right → fix in main repo, new round.
B55: B · Ground-truth error | C55: Client model or hand calculation is wrong; app is right → erratum, inform client, do not change the app.
B56: C · Definition difference | C56: Both internally consistent, different definition → decision note; client chooses.
B57: D · Presentation / rounding | C57: Same value, different display (blank vs 0, fraction vs %, 2 decimals, aux columns).
B58: E · Alignment / timing | C58: Period shift between the two runs (planning month, actuals, lead-time offset).
B59: F · Test artefact | C59: One side contains edits/overrides the other does not → reject the pair, build clean sources.

Sheet GT Register
A1: Ground-truth register (§3)
A2: A ground truth is only a ground truth once it is frozen: file + hash + parameters + owner. Never modify a frozen GT — a new version is a new ID.
A4: GT-ID | B4: File name | C4: SHA-256 | D4: Type | E4: Planning month | F4: Actuals months | G4: Site | H4: Model version (VBA / spec) | I4: Frozen by | J4: Frozen on | K4: Errata (known errors in the source) | L4: Storage location | M4: Status | N4: Notes
A5: GT-NLX1-202512-01 | B5: golden_MS_RECONC.xlsm (after CalculateFull) | D5: GT-A | E5: 2025-12 | F5: 12 | G5: NLX1 | K5: PAP formula (1-2) instead of (1-0.2) on 600003822; empty tariff on 150000483 (parallel run July 2026) | L5: %LOCALAPPDATA%\SOPPlanningEngine\ground_truth\GT-NLX1-202512-01 | M5: TO FREEZE | N5: Round 1 — see strategy §9
A6: GT-NLK1-<yyyymm>-01 | B6: first real monthly extract Winterswijk | D6: GT-A | G6: NLK1 | M6: TO FREEZE | N6: Round 2
A7: GT-NLU1-<yyyymm>-01 | B7: first real monthly extract Ankerkade | D7: GT-A | G7: NLU1 | M7: TO FREEZE | N7: Round 3
A8: GT-NLX1-202512-B1 | B8: hand calculation K1–K5 (Calc Chains sheet) | C8: n/a | D8: GT-B | E8: 2025-12 | F8: 12 | G8: NLX1 | H8: functional description (procedure file / LOR) version … | L8: this workbook | M8: TO FILL | N8: Independent of VBA and Python
A9: PAIR-AB-2026-07 (not frozen) | B9: test a + b.xlsm ↔ test a + b python.xlsx | D9: test artefact | E9: 2025-12 | F9: 12 | G9: NLX1 | L9: officieel test documenten sop | M9: NOT A GT | N9: End state after tests A/B incl. edits — used for the baseline measurement only
A10: PAIR-CD-2026-07 (not frozen) | B10: test c + D GT.xlsm ↔ test c + d python.xlsx | D10: test artefact | E10: 2025-12 | F10: 12 | G10: NLX1 | L10: officieel test documenten sop | M10: NOT A GT | N10: End state after tests C/D incl. edits — baseline measurement only

Sheet R1 Baseline Parity
A1: R1 — Baseline parity: app export vs. client Excel, cell by cell
A2: Same workbook → Excel macro run → GT-A; app upload → Calculate → export; python tools/ground_truth_diff.py. Expected: Planning Δ=0 on all lines; Values Δ=0 except erratum cells.
A4: Run | B4: GT-ID | C4: App commit | D4: Sheet | E4: Cells compared | F4: Cells equal | G4: Deviations | H4: Rows only in GT | I4: Rows only in app | J4: Max |Δ| | K4: % equal | L4: Tolerance abs / rel | M4: Report file (ground_truth_diff) | N4: Status | O4: Classified? (all deviation classes in register) | P4: Notes
A5: Baseline 25-08-2026 | B5: PAIR-AB-2026-07 | C5: 82f7643 | D5: Planning sheet | E5: 25649 | F5: 25585 | G5: 64 | H5: 0 | I5: 0 | J5: 196.47 | K5: =IF(E5>0,F5/E5,"") | L5: 1e-6 / 1e-9 | M5: gt_ab.md | N5: FAIL | O5: candidate findings 5, 6 | P5: one BOM pair 400000455 ↔ 600007751: 196.47 shifts Dec-2025 → Jan-2026 and drags L03/L04/L06/L07
A6: Baseline 25-08-2026 | B6: PAIR-AB-2026-07 | C6: 82f7643 | D6: Values_Planning sheet | E6: 7501 | F6: 7217 | G6: 284 | H6: 1 | I6: 0 | J6: 5246842 | K6: =IF(E6>0,F6/E6,"") | L6: 1e-6 / 1e-9 | M6: gt_ab.md | N6: FAIL | O6: candidate findings 1, 2, 6 | P6: Values L01 216 cells systematic; consolidation starting stock 5.2M vs 0
A7: Baseline 25-08-2026 | B7: PAIR-CD-2026-07 | C7: 82f7643 | D7: Planning sheet | E7: 25649 | F7: 25522 | G7: 127 | H7: 0 | I7: 0 | J7: 21.8198 | K7: =IF(E7>0,F7/E7,"") | L7: 1e-6 / 1e-9 | M7: gt_cd.md | N7: FAIL | O7: candidate findings 3, 4 | P7: Z_MACH20 L10 ×100 (22.04 vs 0.2204); ZZ_GROUP03 / Z_MACH14–16 0.02–0.03 %
A8: Baseline 25-08-2026 | B8: PAIR-CD-2026-07 | C8: 82f7643 | D8: Values_Planning sheet | E8: 7501 | F8: 7130 | G8: 371 | H8: 1 | I8: 0 | J8: 5246842 | K8: =IF(E8>0,F8/E8,"") | L8: 1e-6 / 1e-9 | M8: gt_cd.md | N8: FAIL | O8: candidate findings 1, 2, 6 | P8: Values L01 216 cells systematic (same as a+b)
A9: Round 1 | B9: GT-NLX1-202512-01 | D9: Planning sheet | K9: =IF(E9>0,F9/E9,"") | L9: 1e-6 / 1e-9 | N9: TODO
A10: Round 1 | B10: GT-NLX1-202512-01 | D10: Values_Planning sheet | K10: =IF(E10>0,F10/E10,"") | L10: 0.01 / – | N10: TODO
A11: Round 2 | B11: GT-NLK1-… | D11: Planning sheet | K11: =IF(E11>0,F11/E11,"") | L11: 1e-6 / 1e-9 | N11: TODO
A12: Round 2 | B12: GT-NLK1-… | D12: Values_Planning sheet | K12: =IF(E12>0,F12/E12,"") | L12: 0.01 / – | N12: TODO
A13: Round 3 | B13: GT-NLU1-… | D13: Planning sheet | K13: =IF(E13>0,F13/E13,"") | L13: 1e-6 / 1e-9 | N13: TODO
A14: Round 3 | B14: GT-NLU1-… | D14: Values_Planning sheet | K14: =IF(E14>0,F14/E14,"") | L14: 0.01 / – | N14: TODO

Sheet R2 Calc Chains
A1: R2 — Calculation chains K1–K5: independent hand calculation (GT-B)
A2: Write the formula from the functional description (not from the VBA, not from the Python). Fill inputs from the source sheets. Three columns, three sources: hand · app · Excel. Any inequality is a finding — even when app and Excel agree.
A4: Chain | B4: Line | C4: Formula (from functional description — cite source) | D4: Input values (value + source sheet/cell) | E4: Expected (hand calculation) | F4: App value | G4: Excel value (GT-A) | H4: Δ app − hand | I4: Δ Excel − hand | J4: Tolerance | K4: Match? | L4: Finding # | M4: Notes
A5: K1 — Purchased raw material with MOQ and lead time · material: ________ period(s): ________ (purchase plan, MOQ rounding, lead-time shift)
A6: K1 | B6: L01 Demand forecast | C6: Forecast sheet value for the period (actuals for actuals months, forecast thereafter) | H6: =IF(AND(ISNUMBER(F6),ISNUMBER(E6)),F6-E6,"") | I6: =IF(AND(ISNUMBER(G6),ISNUMBER(E6)),G6-E6,"") | J6: 1e-06 | K6: =IF(OR(E6="",F6="",G6=""),"TODO",IF(AND(ABS(H6)<=J6,ABS(I6)<=J6),"PASS","FAIL"))
A7: K1 | B7: L02 Dependent demand | C7: Σ over parents: parent L06 production × quantity_per (BOM) | H7: =IF(AND(ISNUMBER(F7),ISNUMBER(E7)),F7-E7,"") | I7: =IF(AND(ISNUMBER(G7),ISNUMBER(E7)),G7-E7,"") | J7: 1e-06 | K7: =IF(OR(E7="",F7="",G7=""),"TODO",IF(AND(ABS(H7)<=J7,ABS(I7)<=J7),"PASS","FAIL"))
A8: K1 | B8: L03 Total demand | C8: L01 + Σ L02 | H8: =IF(AND(ISNUMBER(F8),ISNUMBER(E8)),F8-E8,"") | I8: =IF(AND(ISNUMBER(G8),ISNUMBER(E8)),G8-E8,"") | J8: 1e-06 | K8: =IF(OR(E8="",F8="",G8=""),"TODO",IF(AND(ABS(H8)<=J8,ABS(I8)<=J8),"PASS","FAIL"))
A9: K1 | B9: L05 Minimum target stock | C9: safety stock / target stock from Safety stock sheet | H9: =IF(AND(ISNUMBER(F9),ISNUMBER(E9)),F9-E9,"") | I9: =IF(AND(ISNUMBER(G9),ISNUMBER(E9)),G9-E9,"") | J9: 1e-06 | K9: =IF(OR(E9="",F9="",G9=""),"TODO",IF(AND(ABS(H9)<=J9,ABS(I9)<=J9),"PASS","FAIL"))
A10: K1 | B10: L04 Inventory (running balance) | C10: L04[t−1] + L06 purchase receipt[t] − L03[t]; L04[0] = starting stock (Stock level sheet) | H10: =IF(AND(ISNUMBER(F10),ISNUMBER(E10)),F10-E10,"") | I10: =IF(AND(ISNUMBER(G10),ISNUMBER(E10)),G10-E10,"") | J10: 1e-06 | K10: =IF(OR(E10="",F10="",G10=""),"TODO",IF(AND(ABS(H10)<=J10,ABS(I10)<=J10),"PASS","FAIL"))
A11: K1 | B11: L06 Purchase receipt | C11: if L04 without order < L05: order = max(MOQ, shortage) rounded up to MOQ multiple (Purchase sheet: MOQ, lead time) | H11: =IF(AND(ISNUMBER(F11),ISNUMBER(E11)),F11-E11,"") | I11: =IF(AND(ISNUMBER(G11),ISNUMBER(E11)),G11-E11,"") | J11: 1e-06 | K11: =IF(OR(E11="",F11="",G11=""),"TODO",IF(AND(ABS(H11)<=J11,ABS(I11)<=J11),"PASS","FAIL"))
A12: K1 | B12: L07 Purchase plan | C12: L06 purchase receipt shifted back by the lead time (months) | H12: =IF(AND(ISNUMBER(F12),ISNUMBER(E12)),F12-E12,"") | I12: =IF(AND(ISNUMBER(G12),ISNUMBER(E12)),G12-E12,"") | J12: 1e-06 | K12: =IF(OR(E12="",F12="",G12=""),"TODO",IF(AND(ABS(H12)<=J12,ABS(I12)<=J12),"PASS","FAIL"))
A13: K1 | B13: Values L01 (revenue) | C13: sales price (Average sales price sheet) × L01 volume | H13: =IF(AND(ISNUMBER(F13),ISNUMBER(E13)),F13-E13,"") | I13: =IF(AND(ISNUMBER(G13),ISNUMBER(E13)),G13-E13,"") | J13: 0.01 | K13: =IF(OR(E13="",F13="",G13=""),"TODO",IF(AND(ABS(H13)<=J13,ABS(I13)<=J13),"PASS","FAIL"))
A14: K1 | B14: Values L06 raw material cost | C14: cost per unit (Cost raw material) × purchase volume | H14: =IF(AND(ISNUMBER(F14),ISNUMBER(E14)),F14-E14,"") | I14: =IF(AND(ISNUMBER(G14),ISNUMBER(E14)),G14-E14,"") | J14: 0.01 | K14: =IF(OR(E14="",F14="",G14=""),"TODO",IF(AND(ABS(H14)<=J14,ABS(I14)<=J14),"PASS","FAIL"))
A16: K2 — Bulk product with BOM to K1 · material: ________ (parent → child dependent demand, safety/target stock)
A17: K2 | B17: L01 Demand forecast | C17: Forecast sheet | H17: =IF(AND(ISNUMBER(F17),ISNUMBER(E17)),F17-E17,"") | I17: =IF(AND(ISNUMBER(G17),ISNUMBER(E17)),G17-E17,"") | J17: 1e-06 | K17: =IF(OR(E17="",F17="",G17=""),"TODO",IF(AND(ABS(H17)<=J17,ABS(I17)<=J17),"PASS","FAIL"))
A18: K2 | B18: L03 Total demand | C18: L01 + Σ L02 | H18: =IF(AND(ISNUMBER(F18),ISNUMBER(E18)),F18-E18,"") | I18: =IF(AND(ISNUMBER(G18),ISNUMBER(E18)),G18-E18,"") | J18: 1e-06 | K18: =IF(OR(E18="",F18="",G18=""),"TODO",IF(AND(ABS(H18)<=J18,ABS(I18)<=J18),"PASS","FAIL"))
A19: K2 | B19: L05 Minimum target stock | C19: Safety stock sheet | H19: =IF(AND(ISNUMBER(F19),ISNUMBER(E19)),F19-E19,"") | I19: =IF(AND(ISNUMBER(G19),ISNUMBER(E19)),G19-E19,"") | J19: 1e-06 | K19: =IF(OR(E19="",F19="",G19=""),"TODO",IF(AND(ABS(H19)<=J19,ABS(I19)<=J19),"PASS","FAIL"))
A20: K2 | B20: L06 Production plan | C20: ceil((target − (stock − demand)) / lot size) × lot size; 0 when stock suffices | H20: =IF(AND(ISNUMBER(F20),ISNUMBER(E20)),F20-E20,"") | I20: =IF(AND(ISNUMBER(G20),ISNUMBER(E20)),G20-E20,"") | J20: 1e-06 | K20: =IF(OR(E20="",F20="",G20=""),"TODO",IF(AND(ABS(H20)<=J20,ABS(I20)<=J20),"PASS","FAIL"))
A21: K2 | B21: L04 Inventory | C21: L04[t−1] + L06 production[t] − L03[t] | H21: =IF(AND(ISNUMBER(F21),ISNUMBER(E21)),F21-E21,"") | I21: =IF(AND(ISNUMBER(G21),ISNUMBER(E21)),G21-E21,"") | J21: 1e-06 | K21: =IF(OR(E21="",F21="",G21=""),"TODO",IF(AND(ABS(H21)<=J21,ABS(I21)<=J21),"PASS","FAIL"))
A22: K2 | B22: L08 Dependent requirements (→ K1) | C22: L06 production × quantity_per(K1); must equal K1's L02 with aux = this material (invariant I2) | H22: =IF(AND(ISNUMBER(F22),ISNUMBER(E22)),F22-E22,"") | I22: =IF(AND(ISNUMBER(G22),ISNUMBER(E22)),G22-E22,"") | J22: 1e-06 | K22: =IF(OR(E22="",F22="",G22=""),"TODO",IF(AND(ABS(H22)<=J22,ABS(I22)<=J22),"PASS","FAIL"))
A23: K2 | B23: L07 Capacity utilization (hours) | C23: (production qty / base qty) × standard time per routing step, per machine | H23: =IF(AND(ISNUMBER(F23),ISNUMBER(E23)),F23-E23,"") | I23: =IF(AND(ISNUMBER(G23),ISNUMBER(E23)),G23-E23,"") | J23: 1e-06 | K23: =IF(OR(E23="",F23="",G23=""),"TODO",IF(AND(ABS(H23)<=J23,ABS(I23)<=J23),"PASS","FAIL"))
A24: K2 | B24: Values L01 (revenue) | C24: price × L01 | H24: =IF(AND(ISNUMBER(F24),ISNUMBER(E24)),F24-E24,"") | I24: =IF(AND(ISNUMBER(G24),ISNUMBER(E24)),G24-E24,"") | J24: 0.01 | K24: =IF(OR(E24="",F24="",G24=""),"TODO",IF(AND(ABS(H24)<=J24,ABS(I24)<=J24),"PASS","FAIL"))
A26: K3 — Packaged product with BOM to K2 and packaging goods · material: ________ (two BOM levels, topological order)
A27: K3 | B27: L01 Demand forecast | C27: Forecast sheet | H27: =IF(AND(ISNUMBER(F27),ISNUMBER(E27)),F27-E27,"") | I27: =IF(AND(ISNUMBER(G27),ISNUMBER(E27)),G27-E27,"") | J27: 1e-06 | K27: =IF(OR(E27="",F27="",G27=""),"TODO",IF(AND(ABS(H27)<=J27,ABS(I27)<=J27),"PASS","FAIL"))
A28: K3 | B28: L03 Total demand | C28: L01 + Σ L02 | H28: =IF(AND(ISNUMBER(F28),ISNUMBER(E28)),F28-E28,"") | I28: =IF(AND(ISNUMBER(G28),ISNUMBER(E28)),G28-E28,"") | J28: 1e-06 | K28: =IF(OR(E28="",F28="",G28=""),"TODO",IF(AND(ABS(H28)<=J28,ABS(I28)<=J28),"PASS","FAIL"))
A29: K3 | B29: L06 Production plan | C29: lot-size rule as K2 | H29: =IF(AND(ISNUMBER(F29),ISNUMBER(E29)),F29-E29,"") | I29: =IF(AND(ISNUMBER(G29),ISNUMBER(E29)),G29-E29,"") | J29: 1e-06 | K29: =IF(OR(E29="",F29="",G29=""),"TODO",IF(AND(ABS(H29)<=J29,ABS(I29)<=J29),"PASS","FAIL"))
A30: K3 | B30: L08 Dependent requirements (→ K2 bulk) | C30: L06 × quantity_per(bulk) | H30: =IF(AND(ISNUMBER(F30),ISNUMBER(E30)),F30-E30,"") | I30: =IF(AND(ISNUMBER(G30),ISNUMBER(E30)),G30-E30,"") | J30: 1e-06 | K30: =IF(OR(E30="",F30="",G30=""),"TODO",IF(AND(ABS(H30)<=J30,ABS(I30)<=J30),"PASS","FAIL"))
A31: K3 | B31: L08 Dependent requirements (→ packaging good) | C31: L06 × quantity_per(packaging) | H31: =IF(AND(ISNUMBER(F31),ISNUMBER(E31)),F31-E31,"") | I31: =IF(AND(ISNUMBER(G31),ISNUMBER(E31)),G31-E31,"") | J31: 1e-06 | K31: =IF(OR(E31="",F31="",G31=""),"TODO",IF(AND(ABS(H31)<=J31,ABS(I31)<=J31),"PASS","FAIL"))
A32: K3 | B32: K2 L02 from K3 | C32: must equal the K3 L08 above (I2) — and feed K2's L03 before K2's L06 is computed (topological order) | H32: =IF(AND(ISNUMBER(F32),ISNUMBER(E32)),F32-E32,"") | I32: =IF(AND(ISNUMBER(G32),ISNUMBER(E32)),G32-E32,"") | J32: 1e-06 | K32: =IF(OR(E32="",F32="",G32=""),"TODO",IF(AND(ABS(H32)<=J32,ABS(I32)<=J32),"PASS","FAIL"))
A33: K3 | B33: L04 Inventory | C33: running balance | H33: =IF(AND(ISNUMBER(F33),ISNUMBER(E33)),F33-E33,"") | I33: =IF(AND(ISNUMBER(G33),ISNUMBER(E33)),G33-E33,"") | J33: 1e-06 | K33: =IF(OR(E33="",F33="",G33=""),"TODO",IF(AND(ABS(H33)<=J33,ABS(I33)<=J33),"PASS","FAIL"))
A35: K4 — Machine group with ≥ 2 machines used by K2/K3 · group: ________ machines: ________ period: ________
A36: K4 | B36: L07 Capacity utilization — machine 1 | C36: Σ over materials routed on the machine: (qty / base qty) × std time | H36: =IF(AND(ISNUMBER(F36),ISNUMBER(E36)),F36-E36,"") | I36: =IF(AND(ISNUMBER(G36),ISNUMBER(E36)),G36-E36,"") | J36: 1e-06 | K36: =IF(OR(E36="",F36="",G36=""),"TODO",IF(AND(ABS(H36)<=J36,ABS(I36)<=J36),"PASS","FAIL"))
A37: K4 | B37: L07 Capacity utilization — machine 2 | C37: idem | H37: =IF(AND(ISNUMBER(F37),ISNUMBER(E37)),F37-E37,"") | I37: =IF(AND(ISNUMBER(G37),ISNUMBER(E37)),G37-E37,"") | J37: 1e-06 | K37: =IF(OR(E37="",F37="",G37=""),"TODO",IF(AND(ABS(H37)<=J37,ABS(I37)<=J37),"PASS","FAIL"))
A38: K4 | B38: L07 Capacity utilization — group | C38: mill groups: MAX of machines; other groups: Σ — record which rule applies (I7) | H38: =IF(AND(ISNUMBER(F38),ISNUMBER(E38)),F38-E38,"") | I38: =IF(AND(ISNUMBER(G38),ISNUMBER(E38)),G38-E38,"") | J38: 1e-06 | K38: =IF(OR(E38="",F38="",G38=""),"TODO",IF(AND(ABS(H38)<=J38,ABS(I38)<=J38),"PASS","FAIL"))
A39: K4 | B39: L11 Shift availability | C39: shift system hours per month (FTE sheet: 2-shift / 3-shift / 24/7) × availability % | H39: =IF(AND(ISNUMBER(F39),ISNUMBER(E39)),F39-E39,"") | I39: =IF(AND(ISNUMBER(G39),ISNUMBER(E39)),G39-E39,"") | J39: 1e-06 | K39: =IF(OR(E39="",F39="",G39=""),"TODO",IF(AND(ABS(H39)<=J39,ABS(I39)<=J39),"PASS","FAIL"))
A40: K4 | B40: L09 Available capacity | C40: L11 × OEE (OEE + Machine groups sheet; unlimited machines never bottleneck) | H40: =IF(AND(ISNUMBER(F40),ISNUMBER(E40)),F40-E40,"") | I40: =IF(AND(ISNUMBER(G40),ISNUMBER(E40)),G40-E40,"") | J40: 1e-06 | K40: =IF(OR(E40="",F40="",G40=""),"TODO",IF(AND(ABS(H40)<=J40,ABS(I40)<=J40),"PASS","FAIL"))
A41: K4 | B41: L10 Utilization rate | C41: L07 ÷ L09 (fraction 0–1 — record the unit used by each source) | H41: =IF(AND(ISNUMBER(F41),ISNUMBER(E41)),F41-E41,"") | I41: =IF(AND(ISNUMBER(G41),ISNUMBER(E41)),G41-E41,"") | J41: 1e-06 | K41: =IF(OR(E41="",F41="",G41=""),"TODO",IF(AND(ABS(H41)<=J41,ABS(I41)<=J41),"PASS","FAIL"))
A42: K4 | B42: L12 FTE requirements | C42: total hours ÷ (FTE hours per year ÷ 12) — or staffing norm × hours when workbench norms exist | H42: =IF(AND(ISNUMBER(F42),ISNUMBER(E42)),F42-E42,"") | I42: =IF(AND(ISNUMBER(G42),ISNUMBER(E42)),G42-E42,"") | J42: 0.001 | K42: =IF(OR(E42="",F42="",G42=""),"TODO",IF(AND(ABS(H42)<=J42,ABS(I42)<=J42),"PASS","FAIL"))
A44: K5 — FTE row + the 20 consolidation lines for one month · group/truck/control room: ________ month: ________
A45: K5 | B45: L12 FTE — production group | C45: as K4 | H45: =IF(AND(ISNUMBER(F45),ISNUMBER(E45)),F45-E45,"") | I45: =IF(AND(ISNUMBER(G45),ISNUMBER(E45)),G45-E45,"") | J45: 0.001 | K45: =IF(OR(E45="",F45="",G45=""),"TODO",IF(AND(ABS(H45)<=J45,ABS(I45)<=J45),"PASS","FAIL"))
A46: K5 | B46: L12 FTE — trucks | C46: tons ÷ tons per truck → hours → FTE (Material master: Ton per truck, FTE requirements) | H46: =IF(AND(ISNUMBER(F46),ISNUMBER(E46)),F46-E46,"") | I46: =IF(AND(ISNUMBER(G46),ISNUMBER(E46)),G46-E46,"") | J46: 0.001 | K46: =IF(OR(E46="",F46="",G46=""),"TODO",IF(AND(ABS(H46)<=J46,ABS(I46)<=J46),"PASS","FAIL"))
A47: K5 | B47: L12 FTE — control room | C47: fixed FTE per shift × shifts | H47: =IF(AND(ISNUMBER(F47),ISNUMBER(E47)),F47-E47,"") | I47: =IF(AND(ISNUMBER(G47),ISNUMBER(E47)),G47-E47,"") | J47: 0.001 | K47: =IF(OR(E47="",F47="",G47=""),"TODO",IF(AND(ABS(H47)<=J47,ABS(I47)<=J47),"PASS","FAIL"))
A48: K5 | B48: Consolidation: TURNOVER | C48: Σ Values L01 over all materials | H48: =IF(AND(ISNUMBER(F48),ISNUMBER(E48)),F48-E48,"") | I48: =IF(AND(ISNUMBER(G48),ISNUMBER(E48)),G48-E48,"") | J48: 0.01 | K48: =IF(OR(E48="",F48="",G48=""),"TODO",IF(AND(ABS(H48)<=J48,ABS(I48)<=J48),"PASS","FAIL"))
A49: K5 | B49: Consolidation: RAW MATERIAL COST | C49: Σ raw material cost | H49: =IF(AND(ISNUMBER(F49),ISNUMBER(E49)),F49-E49,"") | I49: =IF(AND(ISNUMBER(G49),ISNUMBER(E49)),G49-E49,"") | J49: 0.01 | K49: =IF(OR(E49="",F49="",G49=""),"TODO",IF(AND(ABS(H49)<=J49,ABS(I49)<=J49),"PASS","FAIL"))
A50: K5 | B50: Consolidation: MACHINE COST | C50: Σ L07 hours × variable cost per hour (Cost machine hour) | H50: =IF(AND(ISNUMBER(F50),ISNUMBER(E50)),F50-E50,"") | I50: =IF(AND(ISNUMBER(G50),ISNUMBER(E50)),G50-E50,"") | J50: 0.01 | K50: =IF(OR(E50="",F50="",G50=""),"TODO",IF(AND(ABS(H50)<=J50,ABS(I50)<=J50),"PASS","FAIL"))
A51: K5 | B51: Consolidation: DIRECT FTE COST | C51: Σ L12 × cost per FTE per year ÷ 12 — scope: production FTE only vs. all groups (definition C-decision!) | H51: =IF(AND(ISNUMBER(F51),ISNUMBER(E51)),F51-E51,"") | I51: =IF(AND(ISNUMBER(G51),ISNUMBER(E51)),G51-E51,"") | J51: 0.01 | K51: =IF(OR(E51="",F51="",G51=""),"TODO",IF(AND(ABS(H51)<=J51,ABS(I51)<=J51),"PASS","FAIL"))
A52: K5 | B52: Consolidation: COST OF GOODS | C52: raw material + machine + direct FTE (+ other cost lines per spec) | H52: =IF(AND(ISNUMBER(F52),ISNUMBER(E52)),F52-E52,"") | I52: =IF(AND(ISNUMBER(G52),ISNUMBER(E52)),G52-E52,"") | J52: 0.01 | K52: =IF(OR(E52="",F52="",G52=""),"TODO",IF(AND(ABS(H52)<=J52,ABS(I52)<=J52),"PASS","FAIL"))
A53: K5 | B53: Consolidation: GROSS MARGIN | C53: TURNOVER − COST OF GOODS | H53: =IF(AND(ISNUMBER(F53),ISNUMBER(E53)),F53-E53,"") | I53: =IF(AND(ISNUMBER(G53),ISNUMBER(E53)),G53-E53,"") | J53: 0.01 | K53: =IF(OR(E53="",F53="",G53=""),"TODO",IF(AND(ABS(H53)<=J53,ABS(I53)<=J53),"PASS","FAIL"))
A54: K5 | B54: Consolidation: EBITDA | C54: GROSS MARGIN − fixed costs (constant per month, Valuation parameters) | H54: =IF(AND(ISNUMBER(F54),ISNUMBER(E54)),F54-E54,"") | I54: =IF(AND(ISNUMBER(G54),ISNUMBER(E54)),G54-E54,"") | J54: 0.01 | K54: =IF(OR(E54="",F54="",G54=""),"TODO",IF(AND(ABS(H54)<=J54,ABS(I54)<=J54),"PASS","FAIL"))
A55: K5 | B55: Consolidation: EBIT | C55: EBITDA − depreciation (constant per month) | H55: =IF(AND(ISNUMBER(F55),ISNUMBER(E55)),F55-E55,"") | I55: =IF(AND(ISNUMBER(G55),ISNUMBER(E55)),G55-E55,"") | J55: 0.01 | K55: =IF(OR(E55="",F55="",G55=""),"TODO",IF(AND(ABS(H55)<=J55,ABS(I55)<=J55),"PASS","FAIL"))
A56: K5 | B56: Consolidation: INVENTORY VALUE | C56: Σ L04 × cost per unit; starting stock value must be filled (finding 2) | H56: =IF(AND(ISNUMBER(F56),ISNUMBER(E56)),F56-E56,"") | I56: =IF(AND(ISNUMBER(G56),ISNUMBER(E56)),G56-E56,"") | J56: 0.01 | K56: =IF(OR(E56="",F56="",G56=""),"TODO",IF(AND(ABS(H56)<=J56,ABS(I56)<=J56),"PASS","FAIL"))
... A61: K5 | B61: Remaining consolidation lines (4) | C61: list from Values_Planning sheet '13. Consolidation' — add rows as needed | H61: =IF(AND(ISNUMBER(F61),ISNUMBER(E61)),F61-E61,"") | I61: =IF(AND(ISNUMBER(G61),ISNUMBER(E61)),G61-E61,"") | J61: 0.01 | K61: =IF(OR(E61="",F61="",G61=""),"TODO",IF(AND(ABS(H61)<=J61,ABS(I61)<=J61),"PASS","FAIL"))

Sheet R4 Invariants
A1: R4 — Invariants (GT-D): identities that must always hold, also on real monthly extracts
A2: Sample ≥ 10 materials and ALL machines per invariant. Fill LHS/RHS from the app export (a worksheet with your own formulas is fine, as long as the formulas do not come from the app).
A4: Invariant | B4: Identity | C4: Material / machine | D4: Period | E4: Left-hand side (from export) | F4: Right-hand side (computed) | G4: Δ | H4: Tolerance | I4: Match? | J4: Notes
A5: I1 Demand build-up | B5: L03 Total demand = L01 Demand forecast + Σ L02 Dependent demand | G5: =IF(AND(ISNUMBER(E5),ISNUMBER(F5)),E5-F5,"") | H5: 1e-06 | I5: =IF(OR(E5="",F5=""),"TODO",IF(ABS(G5)<=H5,"PASS","FAIL"))
G6: =IF(AND(ISNUMBER(E6),ISNUMBER(F6)),E6-F6,"") | H6: 1e-06 | I6: =IF(OR(E6="",F6=""),"TODO",IF(ABS(G6)<=H6,"PASS","FAIL"))
G7: =IF(AND(ISNUMBER(E7),ISNUMBER(F7)),E7-F7,"") | H7: 1e-06 | I7: =IF(OR(E7="",F7=""),"TODO",IF(ABS(G7)<=H7,"PASS","FAIL"))
A8: I2 Parent–child mirror | B8: L02 (child, aux = parent) = L08 (parent, aux = child) — cell by cell | G8: =IF(AND(ISNUMBER(E8),ISNUMBER(F8)),E8-F8,"") | H8: 1e-06 | I8: =IF(OR(E8="",F8=""),"TODO",IF(ABS(G8)<=H8,"PASS","FAIL"))
G9: =IF(AND(ISNUMBER(E9),ISNUMBER(F9)),E9-F9,"") | H9: 1e-06 | I9: =IF(OR(E9="",F9=""),"TODO",IF(ABS(G9)<=H9,"PASS","FAIL"))
G10: =IF(AND(ISNUMBER(E10),ISNUMBER(F10)),E10-F10,"") | H10: 1e-06 | I10: =IF(OR(E10="",F10=""),"TODO",IF(ABS(G10)<=H10,"PASS","FAIL"))
A11: I3 Stock balance | B11: L04[t] = L04[t−1] + L06 production[t] + L06 purchase receipt[t] − L03[t]; L04[0] = starting stock | G11: =IF(AND(ISNUMBER(E11),ISNUMBER(F11)),E11-F11,"") | H11: 1e-06 | I11: =IF(OR(E11="",F11=""),"TODO",IF(ABS(G11)<=H11,"PASS","FAIL"))
G12: =IF(AND(ISNUMBER(E12),ISNUMBER(F12)),E12-F12,"") | H12: 1e-06 | I12: =IF(OR(E12="",F12=""),"TODO",IF(ABS(G12)<=H12,"PASS","FAIL"))
G13: =IF(AND(ISNUMBER(E13),ISNUMBER(F13)),E13-F13,"") | H13: 1e-06 | I13: =IF(OR(E13="",F13=""),"TODO",IF(ABS(G13)<=H13,"PASS","FAIL"))
A14: I4 Target stock | B14: where demand allows: L04[t] ≥ L05[t]; an order arises exactly when the balance without order would drop below L05 | G14: =IF(AND(ISNUMBER(E14),ISNUMBER(F14)),E14-F14,"") | H14: 1e-06 | I14: =IF(OR(E14="",F14=""),"TODO",IF(ABS(G14)<=H14,"PASS","FAIL"))
G15: =IF(AND(ISNUMBER(E15),ISNUMBER(F15)),E15-F15,"") | H15: 1e-06 | I15: =IF(OR(E15="",F15=""),"TODO",IF(ABS(G15)<=H15,"PASS","FAIL"))
G16: =IF(AND(ISNUMBER(E16),ISNUMBER(F16)),E16-F16,"") | H16: 1e-06 | I16: =IF(OR(E16="",F16=""),"TODO",IF(ABS(G16)<=H16,"PASS","FAIL"))
A17: I5 MOQ / lot size | B17: every purchase order ≥ MOQ; every production order ≥ lot size (when set) | G17: =IF(AND(ISNUMBER(E17),ISNUMBER(F17)),E17-F17,"") | H17: 1e-06 | I17: =IF(OR(E17="",F17=""),"TODO",IF(ABS(G17)<=H17,"PASS","FAIL"))
G18: =IF(AND(ISNUMBER(E18),ISNUMBER(F18)),E18-F18,"") | H18: 1e-06 | I18: =IF(OR(E18="",F18=""),"TODO",IF(ABS(G18)<=H18,"PASS","FAIL"))
G19: =IF(AND(ISNUMBER(E19),ISNUMBER(F19)),E19-F19,"") | H19: 1e-06 | I19: =IF(OR(E19="",F19=""),"TODO",IF(ABS(G19)<=H19,"PASS","FAIL"))
A20: I6 Utilization rate | B20: L10 = L07 capacity utilization ÷ L09 available capacity (fraction) | G20: =IF(AND(ISNUMBER(E20),ISNUMBER(F20)),E20-F20,"") | H20: 1e-06 | I20: =IF(OR(E20="",F20=""),"TODO",IF(ABS(G20)<=H20,"PASS","FAIL"))
G21: =IF(AND(ISNUMBER(E21),ISNUMBER(F21)),E21-F21,"") | H21: 1e-06 | I21: =IF(OR(E21="",F21=""),"TODO",IF(ABS(G21)<=H21,"PASS","FAIL"))
G22: =IF(AND(ISNUMBER(E22),ISNUMBER(F22)),E22-F22,"") | H22: 1e-06 | I22: =IF(OR(E22="",F22=""),"TODO",IF(ABS(G22)<=H22,"PASS","FAIL"))
A23: I7 Group rule | B23: mill group: L07 group = MAX(L07 machines); other groups: Σ — record per group which rule applies | G23: =IF(AND(ISNUMBER(E23),ISNUMBER(F23)),E23-F23,"") | H23: 1e-06 | I23: =IF(OR(E23="",F23=""),"TODO",IF(ABS(G23)<=H23,"PASS","FAIL"))
G24: =IF(AND(ISNUMBER(E24),ISNUMBER(F24)),E24-F24,"") | H24: 1e-06 | I24: =IF(OR(E24="",F24=""),"TODO",IF(ABS(G24)<=H24,"PASS","FAIL"))
G25: =IF(AND(ISNUMBER(E25),ISNUMBER(F25)),E25-F25,"") | H25: 1e-06 | I25: =IF(OR(E25="",F25=""),"TODO",IF(ABS(G25)<=H25,"PASS","FAIL"))
A26: I8 Revenue | B26: Values L01 = sales price × Planning L01 per material/period | G26: =IF(AND(ISNUMBER(E26),ISNUMBER(F26)),E26-F26,"") | H26: 0.01 | I26: =IF(OR(E26="",F26=""),"TODO",IF(ABS(G26)<=H26,"PASS","FAIL"))
G27: =IF(AND(ISNUMBER(E27),ISNUMBER(F27)),E27-F27,"") | H27: 0.01 | I27: =IF(OR(E27="",F27=""),"TODO",IF(ABS(G27)<=H27,"PASS","FAIL"))
G28: =IF(AND(ISNUMBER(E28),ISNUMBER(F28)),E28-F28,"") | H28: 0.01 | I28: =IF(OR(E28="",F28=""),"TODO",IF(ABS(G28)<=H28,"PASS","FAIL"))
A29: I9 Consolidation chain | B29: GROSS MARGIN = TURNOVER − COST OF GOODS; EBITDA = GROSS MARGIN − fixed; EBIT = EBITDA − depreciation (last two differences constant per month) | G29: =IF(AND(ISNUMBER(E29),ISNUMBER(F29)),E29-F29,"") | H29: 0.01 | I29: =IF(OR(E29="",F29=""),"TODO",IF(ABS(G29)<=H29,"PASS","FAIL"))
G30: =IF(AND(ISNUMBER(E30),ISNUMBER(F30)),E30-F30,"") | H30: 0.01 | I30: =IF(OR(E30="",F30=""),"TODO",IF(ABS(G30)<=H30,"PASS","FAIL"))
G31: =IF(AND(ISNUMBER(E31),ISNUMBER(F31)),E31-F31,"") | H31: 0.01 | I31: =IF(OR(E31="",F31=""),"TODO",IF(ABS(G31)<=H31,"PASS","FAIL"))
A32: I10 Valid numbers | B32: no NaN / ∞ / blank where a number belongs; no negative L06 / L07 | G32: =IF(AND(ISNUMBER(E32),ISNUMBER(F32)),E32-F32,"") | H32: 0 | I32: =IF(OR(E32="",F32=""),"TODO",IF(ABS(G32)<=H32,"PASS","FAIL"))
G33: =IF(AND(ISNUMBER(E33),ISNUMBER(F33)),E33-F33,"") | H33: 0 | I33: =IF(OR(E33="",F33=""),"TODO",IF(ABS(G33)<=H33,"PASS","FAIL"))
G34: =IF(AND(ISNUMBER(E34),ISNUMBER(F34)),E34-F34,"") | H34: 0 | I34: =IF(OR(E34="",F34=""),"TODO",IF(ABS(G34)<=H34,"PASS","FAIL"))
A35: I11 Line completeness | B35: all expected line types present for every active material (EXPECTED_LINE_TYPES) | G35: =IF(AND(ISNUMBER(E35),ISNUMBER(F35)),E35-F35,"") | H35: 0 | I35: =IF(OR(E35="",F35=""),"TODO",IF(ABS(G35)<=H35,"PASS","FAIL"))
G36: =IF(AND(ISNUMBER(E36),ISNUMBER(F36)),E36-F36,"") | H36: 0 | I36: =IF(OR(E36="",F36=""),"TODO",IF(ABS(G36)<=H36,"PASS","FAIL"))
G37: =IF(AND(ISNUMBER(E37),ISNUMBER(F37)),E37-F37,"") | H37: 0 | I37: =IF(OR(E37="",F37=""),"TODO",IF(ABS(G37)<=H37,"PASS","FAIL"))

Sheet R3 Mirror Edits
A1: R3 — Mirror edits (GT-C): the same edit in the app and in the client Excel, compare the cascade
A2: From docs/parallelle-run-methodiek.md: the twelve 1-to-1 mirrorable edits. Machine edits, valuation parameters, purchase receipts and new products are NOT mirrorable — they are proven via R2 and R4 instead.
A4: ID | B4: Checklist ref | C4: Edit (same in app AND in a copy of the GT-A workbook) | D4: Material / machine | E4: Input: from → to | F4: Expected propagation | G4: Cells to compare (line · period) | H4: App value | I4: Excel value (after CalculateFull) | J4: Δ | K4: Tolerance | L4: Match? | M4: Status after Reset (vs original GT-A = Δ0) | N4: Evidence | O4: Notes
A5: M01 | B5: A5 | C5: Sales price ×2 | E5: price p → 2p | F5: Values L01 (revenue) ×2 for that material; TURNOVER, GROSS MARGIN, EBITDA, EBIT move by the same €; volumes unchanged | G5: Values L01 · all periods; TURNOVER · P1 | J5: =IF(AND(ISNUMBER(H5),ISNUMBER(I5)),H5-I5,"") | K5: 0.01 | L5: =IF(OR(H5="",I5=""),"TODO",IF(ABS(J5)<=K5,"PASS","FAIL"))
A6: M02 | B6: A12 | C6: Raw material cost ×4 | E6: cost c → 4c | F6: RAW MATERIAL COST line ×4 for that material; COST OF GOODS, margins move; volumes unchanged | G6: Values raw cost · P1–P3 | J6: =IF(AND(ISNUMBER(H6),ISNUMBER(I6)),H6-I6,"") | K6: 0.01 | L6: =IF(OR(H6="",I6=""),"TODO",IF(ABS(J6)<=K6,"PASS","FAIL"))
A7: M03 | B7: C1 | C7: Forecast edit (L01 ×2 for one period) | E7: L01[P1] v → 2v | F7: L03, L04, L06 of the material; L02/L08 of its components; L07 of routed machines | G7: L03/L04/L06 · P1–P3; child L02 · P1 | J7: =IF(AND(ISNUMBER(H7),ISNUMBER(I7)),H7-I7,"") | K7: 1e-06 | L7: =IF(OR(H7="",I7=""),"TODO",IF(ABS(J7)<=K7,"PASS","FAIL"))
A8: M04 | B8: C3 | C8: Cascade to child component (L06 of a parent with BOM) | E8: L06[P2] → +Δ | F8: child L02 (aux = parent) = parent L08 (aux = child) = Δ × quantity_per; child L03/L04/L06 follow | G8: child L02/L08 · P2 | J8: =IF(AND(ISNUMBER(H8),ISNUMBER(I8)),H8-I8,"") | K8: 1e-06 | L8: =IF(OR(H8="",I8=""),"TODO",IF(ABS(J8)<=K8,"PASS","FAIL"))
A9: M05 | B9: C4 | C9: Combination L01 (material X) then L06 (material Y) | E9: two edits in sequence | F9: final state identical in both; order-independent for independent materials | G9: X L03 · P1; Y L04 · P1–P2 | J9: =IF(AND(ISNUMBER(H9),ISNUMBER(I9)),H9-I9,"") | K9: 1e-06 | L9: =IF(OR(H9="",I9=""),"TODO",IF(ABS(J9)<=K9,"PASS","FAIL"))
A10: M06 | B10: C5 | C10: Bulk edit: 3 months of one line | E10: L01[P1..P3] → v | F10: cascade once, all three periods | G10: L03/L06 · P1–P3 | J10: =IF(AND(ISNUMBER(H10),ISNUMBER(I10)),H10-I10,"") | K10: 1e-06 | L10: =IF(OR(H10="",I10=""),"TODO",IF(ABS(J10)<=K10,"PASS","FAIL"))
A11: M07 | B11: C10 | C11: L05 minimum target stock, multi-month | E11: L05[P1..P3] → t | F11: production/purchase order arises where L04 would drop below t | G11: L04/L06 · P1–P4 | J11: =IF(AND(ISNUMBER(H11),ISNUMBER(I11)),H11-I11,"") | K11: 1e-06 | L11: =IF(OR(H11="",I11=""),"TODO",IF(ABS(J11)<=K11,"PASS","FAIL"))
A12: M08 | B12: C11 | C12: L01 edited twice on the same cell | E12: v → v1 → v2 | F12: end state = v2 in both; undo returns to v (app) — Excel: re-enter v | G12: L03 · P1 | J12: =IF(AND(ISNUMBER(H12),ISNUMBER(I12)),H12-I12,"") | K12: 1e-06 | L12: =IF(OR(H12="",I12=""),"TODO",IF(ABS(J12)<=K12,"PASS","FAIL"))
A13: M09 | B13: E8 | C13: L01 edit via top-movers table | E13: L01[P1] → v | F13: same cascade as M03 (entry point does not matter) | G13: L03/L06 · P1 | J13: =IF(AND(ISNUMBER(H13),ISNUMBER(I13)),H13-I13,"") | K13: 1e-06 | L13: =IF(OR(H13="",I13=""),"TODO",IF(ABS(J13)<=K13,"PASS","FAIL"))
A14: M10 | B14: E12 | C14: L01 edit, then reopen chart analysis | E14: L01[P1] → v | F14: analysis panel uses new numbers; Excel cell equal | G14: L01/L03 · P1 | J14: =IF(AND(ISNUMBER(H14),ISNUMBER(I14)),H14-I14,"") | K14: 1e-06 | L14: =IF(OR(H14="",I14=""),"TODO",IF(ABS(J14)<=K14,"PASS","FAIL"))
A15: M11 | B15: F16 | C15: L01 edit under an active material group | E15: L01[P1] → v | F15: scoping does not change the numbers; Excel equal | G15: L03 · P1 | J15: =IF(AND(ISNUMBER(H15),ISNUMBER(I15)),H15-I15,"") | K15: 1e-06 | L15: =IF(OR(H15="",I15=""),"TODO",IF(ABS(J15)<=K15,"PASS","FAIL"))
A16: M12 | B16: H2 | C16: L01 edit → export | E16: L01[P1] → v | F16: exported cell = edited value; ground_truth_diff vs mirror workbook Δ=0 | G16: export L01/L03 · P1 | J16: =IF(AND(ISNUMBER(H16),ISNUMBER(I16)),H16-I16,"") | K16: 1e-06 | L16: =IF(OR(H16="",I16=""),"TODO",IF(ABS(J16)<=K16,"PASS","FAIL"))

Sheet Functional Checks A-I
A1: Functional checks A–I (UI behaviour, sessions, cascade, products, analysis, groups, machines, exports)
A2: English edition of docs/checklist-manuele-validatie.md. Sections can be run separately; A → B first. Paste a screenshot per check into the evidence folder.
A4: ID | B4: Section | C4: Check | D4: Steps / input | E4: Expected result | F4: GT source | G4: Status | H4: Tester | I4: Date | J4: Evidence (screenshot / file) | K4: Notes (what you SAW, not what should have been there)
A5: A. Master data in the app
A6: A1 | B6: Master data in the app | C6: Status card | D6: Open the Config tab. | E6: Card 'Master data' shows 'Master data in the app, version N' with counts per dataset (or the import button if nothing is there — import the workbook first). | F6: UI | G6: TODO
A7: A2 | B7: Master data in the app | C7: Rename a material | D7: Open the materials grid, change one material name (e.g. append ' TEST'), save. | E7: Message 'Master data saved (version N+1). Recalculate sessions to apply.' Grid shows the new name. | F7: UI | G7: TODO
A8: A3 | B8: Master data in the app | C8: Name flows through after recalculation | D8: Go to the active instance and click Calculate. | E8: The new name is in the planning table for that material — also when the instance runs on a workbook. | F8: UI | G8: TODO
A9: A4 | B9: Master data in the app | C9: Revert | D9: Set the name back via the grid and recalculate. | E9: Original name back in the table; version counter +1 again. | F9: UI | G9: TODO
A10: A5 | B10: Master data in the app | C10: Price change flows into finance | D10: In the sales prices dataset change one material's price strongly (e.g. ×2), save, recalculate. | E10: Revenue of that material moves proportionally; other materials unchanged. Revert + recalculate afterwards. | F10: GT-C M01 | G10: TODO
A11: A6 | B11: Master data in the app | C11: Invalid input is rejected | D11: Enter text such as 'abc' in a numeric field (safety stock or price) and try to save. | E11: Clear error message; nothing saved (version unchanged, grid value unchanged after reopening). | F11: UI | G11: TODO
A12: A7 | B12: Master data in the app | C12: Re-import with diff confirmation | D12: Import the same (or a new) workbook again via the master-data card. | E12: The app first shows a difference overview (counts / changed keys) and overwrites only after explicit confirmation. | F12: UI | G12: TODO
A13: A8 | B13: Master data in the app | C13: Deactivate a material | D13: Switch off the Active flag of one (small) material, save, recalculate. | E13: Material disappears from the planning (no lines). Re-activate + recalculate: material is back with the same numbers as before. | F13: GT-E | G13: TODO
A14: A9 | B14: Master data in the app | C14: Edit machine data | D14: Change the OEE of a machine in the master-data grid and recalculate. | E14: Utilization / capacity moves at the next calculation. | F14: GT-B K4 | G14: TODO
A15: A10 | B15: Master data in the app | C15: Edit safety stock | D15: Raise the safety stock of a material and recalculate. | E15: Stock planning (L04/L05) shifts upward. | F15: GT-C M07 | G15: TODO
A16: A11 | B16: Master data in the app | C16: Edit valuation parameters | D16: Change a valuation parameter (e.g. direct FTE cost) and recalculate. | E16: EBIT / ROCE on the dashboard move. | F16: GT-B K5 | G16: TODO
A17: A12 | B17: Master data in the app | C17: Edit raw material cost | D17: Change the raw material cost of a material and recalculate. | E17: Contribution margin / cost of that material move. | F17: GT-C M02 | G17: TODO
A18: B. Sessions & persistence
A19: B1 | B19: Sessions & persistence | C19: New instance | D19: Create a second instance, upload the workbook, Calculate. | E19: Table filled; periods run from the planning month + 12 months ahead; no errors. | F19: UI | G19: TODO
A20: B2 | B20: Sessions & persistence | C20: Switch without leakage | D20: Switch a few times between both instances. | E20: Values, config fields (site, forecast months, valuation) and filters always belong to the chosen instance; nothing 'leaks' from the previous one. | F20: UI | G20: TODO
A21: B3 | B21: Sessions & persistence | C21: Rename instance | D21: Rename the second instance. | E21: New name visible everywhere (list, header) and persists after restart. | F21: UI | G21: TODO
A22: B4 | B22: Sessions & persistence | C22: Change parameters | D22: In the second instance change the planning month or the number of actuals months and recalculate. | E22: Period columns shift; the first instance keeps its own parameters. | F22: UI | G22: TODO
A23: B5 | B23: Sessions & persistence | C23: Restart | D23: Close the app completely and start again. | E23: Both instances still there; after warm-up they show the same numbers, names and parameters as before the restart. Export before and after → ground_truth_diff Δ=0. | F23: GT-E | G23: TODO
A24: B6 | B24: Sessions & persistence | C24: Config per instance after restart | D24: After the restart switch to the second instance and open the Config tab. | E24: Config fields show the values of THIS instance, not those of the first loaded instance. | F24: UI | G24: TODO
A25: B7 | B25: Sessions & persistence | C25: Third instance | D25: Create a third instance next to the two existing ones. | E25: All three are separate in the Files list with their own numbers. | F25: UI | G25: TODO
A26: B8 | B26: Sessions & persistence | C26: Delete instance | D26: Delete one instance. | E26: The instance is gone; the other instances and their data remain intact. | F26: UI | G26: TODO
A27: B9 | B27: Sessions & persistence | C27: Save and load a scenario | D27: Save a scenario inside an instance, make an edit, load the scenario back. | E27: The instance returns to the saved state. | F27: UI | G27: TODO
A28: B10 | B28: Sessions & persistence | C28: Config isolation on edit | D28: Make a config change in instance A; check instance B. | E28: Instance B untouched (no config leakage between instances). | F28: UI | G28: TODO
A29: C. Edits & cascade
A30: C1 | B30: Edits & cascade | C30: Forecast edit cascades | D30: Change one L01 cell (demand forecast) strongly, e.g. ×2. | E30: L03/L04/L06 of that material move; the machine chart of the involved machine group changes; table and chart tell the same story. | F30: GT-C M03 | G30: TODO
A31: C2 | B31: Edits & cascade | C31: Undo | D31: Undo the edit. | E31: All derived lines exactly back to the old values. | F31: GT-E | G31: TODO
A32: C3 | B32: Edits & cascade | C32: Cascade to components | D32: Change the production plan (L06) of an end product with a BOM. | E32: Derived demand (L02/L08) of its components moves — parent → child chain is right. | F32: GT-C M04 | G32: TODO
A33: C4 | B33: Edits & cascade | C33: Combination + restart (replay) | D33: Make two edits after each other (first L01, then L06 of another material), note two derived values, restart the app. | E33: After the restart exactly the same end values — saved edits are replayed in the right order. | F33: GT-C M05 | G33: TODO
A34: C5 | B34: Edits & cascade | C34: Bulk edit | D34: Select several periods of a line (drag) and change them in one go. | E34: All selected cells get the new value; the cascade runs once, cleanly. | F34: GT-C M06 | G34: TODO
A35: C6 | B35: Edits & cascade | C35: Starting stock edit (L04) | D35: Change the starting stock of a material. | E35: The stock line (L04) shifts over the whole horizon and production/purchase planning reacts where stock would drop below safety stock. | F35: GT-D I3 | G35: TODO
A36: C7 | B36: Edits & cascade | C36: Reset | D36: Click Reset after the edits above. | E36: Everything back to baseline; the edits list is empty; starting-stock and bulk edits are gone too. | F36: GT-E | G36: TODO
A37: C8 | B37: Edits & cascade | C37: Comment | D37: Put a comment on a cell, restart the app. | E37: Comment indicator visible and the text is preserved. | F37: UI | G37: TODO
A38: C9 | B38: Edits & cascade | C38: Redo after undo | D38: Make an edit, undo, then redo. | E38: Redo restores exactly the edited value and the cascade. | F38: GT-E | G38: TODO
A39: C10 | B39: Edits & cascade | C39: Minimum target stock edit (L05) | D39: Change the minimum target stock of a material. | E39: Production/purchase planning reacts where stock would drop below the target. | F39: GT-C M07 | G39: TODO
A40: C11 | B40: Edits & cascade | C40: Repeated edit on the same cell | D40: Change the same cell twice in a row, then undo. | E40: Undo returns to the original value (not the intermediate one). | F40: GT-C M08 | G40: TODO
A41: C12 | B41: Edits & cascade | C41: Purchase receipt edit (L06 purchase) | D41: Change the purchase receipt of a purchased material. | E41: Stock (L04) and purchase plan (L07) move consistently. | F41: GT-D I3 | G41: TODO
A42: D. Dynamic products
A43: D1 | B43: Dynamic products | C43: Purchased product (MOQ + lead time) | D43: Add a purchased product with MOQ 250 and lead time 2 months. | E43: Purchase lines present; no order smaller than 250; orders shift forward by the lead time. | F43: GT-B K1 | G43: TODO
A44: D2 | B44: Dynamic products | C44: Produced with BOM + routing | D44: Add a produced product with an existing material as component and a machine routing. | E44: Production lines present; the machine group gets extra hours; the component gets dependent demand. | F44: GT-D I2 | G44: TODO
A45: D3 | B45: Dynamic products | C45: Mix product (PAP split) | D45: Add a mix product with 30 % purchased / 70 % produced. | E45: Both purchase and production lines in the given ratio. | F45: GT-B | G45: TODO
A46: D4 | B46: Dynamic products | C46: Financial reconciliation (3 products) | D46: Check revenue and cost of the three test products. | E46: Revenue = price × volume; raw/machine cost reconcile; dashboard totals have grown accordingly. | F46: GT-D I8 | G46: TODO
A47: D5 | B47: Dynamic products | C47: Product uses ANOTHER added product (reported bug) | D47: Add product B that uses test product A (from D1) as BOM component. | E47: A is in the component list (marked 'added'); B saves; A gets dependent demand from B. | F47: GT-D I2 | G47: TODO
A48: D6 | B48: Dynamic products | C48: Edge: MOQ larger than demand | D48: Add a purchased product with a small volume but a large MOQ. | E48: The order is at least the MOQ; surplus builds up stock. | F48: GT-D I5 | G48: TODO
A49: D7 | B49: Dynamic products | C49: Edge: source-file number rejected | D49: Try to add a product with a material number that already exists in the source file. | E49: Clean error message; nothing is added. | F49: UI | G49: TODO
A50: D8 | B50: Dynamic products | C50: Edge: self-reference rejected | D50: Try to save a product that has itself as component. | E50: Error 'cannot be linked to itself'; nothing saved. | F50: UI | G50: TODO
A51: D9 | B51: Dynamic products | C51: Edit product (upsert) | D51: Open an existing test product, change the volume, save. | E51: The planning recalculates with the new value; no duplicate (same number). | F51: UI | G51: TODO
A52: D10 | B52: Dynamic products | C52: Delete + session switch | D52: Switch to the other instance and back; then delete one test product. | E52: Products stay with their own instance; after deletion the product is gone everywhere and the planning is right without it. | F52: UI | G52: TODO
A53: D11 | B53: Dynamic products | C53: Mix boundary values (0 and 1) | D53: Add mix products with production fraction 0 and 1. | E53: Fraction 0 = fully purchased, fraction 1 = fully produced; no dead fields. | F53: GT-B | G53: TODO
A54: D12 | B54: Dynamic products | C54: Starting stock + safety stock | D54: Add a product with a starting stock and a safety stock. | E54: The stock line starts at the starting stock and stays above the safety stock. | F54: GT-D I3/I4 | G54: TODO
... A56: D14 | B56: Dynamic products | C56: Edge: BOM cycle rejected | D56: Try to make two products that use each other as component (A→B→A). | E56: The cycle is rejected with a clear message. | F56: UI | G56: TODO
A57: E. Chart analysis
A58: E1 | B58: Chart analysis | C58: Automatic detection (financial) | D58: Enlarge the financial chart and click 'Analysis'. | E58: Panel shows the largest movement with the explaining products; nothing cut off. | F58: UI | G58: TODO
A59: E2 | B59: Chart analysis | C59: Two points with connector arrow | D59: Click two points in the chart. | E59: An arrow connects the points; the panel explains exactly THAT difference; contributions add up to ~the difference. | F59: GT-D | G59: TODO
A60: E3 | B60: Chart analysis | C60: Volume chart | D60: Analyse a movement in the volume chart. | E60: Same experience; contributions in units instead of euros. | F60: UI | G60: TODO
A61: E4 | B61: Chart analysis | C61: FTE drill to products | D61: Analyse the FTE chart and click through. | E61: You see which products cause the FTE change. | F61: UI | G61: TODO
A62: E5 | B62: Chart analysis | C62: Machine chart analysis | D62: Open the analysis on a machine/capacity chart. | E62: Working analysis with hours per product. | F62: UI | G62: TODO
A63: E6 | B63: Chart analysis | C63: Inventory quality analysis | D63: Open the analysis on the inventory quality chart. | E63: Logical split by categories/products. | F63: UI | G63: TODO
A64: E7 | B64: Chart analysis | C64: Top movers to table | D64: Click 'to table' on the top movers. | E64: The planning table filters on those products; you can change a value directly. | F64: UI | G64: TODO
A65: E8 | B65: Chart analysis | C65: Movers editable (input error) | D65: Change a value via the top-mover table. | E65: The change cascades normally; chart and panel move along. | F65: GT-C M09 | G65: TODO
A66: E9 | B66: Chart analysis | C66: Excel export of the analysis | D66: Export the analysis. | E66: Excel file with the same numbers as the panel. | F66: GT-E | G66: TODO
A67: E10 | B67: Chart analysis | C67: Edge: identical points | D67: Select two points with (almost) the same value. | E67: The panel reports 'no meaningful difference' instead of an empty/wrong breakdown. | F67: UI | G67: TODO
A68: E11 | B68: Chart analysis | C68: Edge: downward movement | D68: Analyse a clear decrease. | E68: Contributions are negative and explain the decrease; signs are right. | F68: UI | G68: TODO
A69: E12 | B69: Chart analysis | C69: Edge: analysis after an edit | D69: Make an edit and reopen the analysis. | E69: The panel uses the new numbers, not the old ones. | F69: GT-C M10 | G69: TODO
... A75: E18 | B75: Chart analysis | C75: Analysis drill and back | D75: Click through on a product in the analysis and back. | E75: The drill shows product detail; 'back' returns cleanly to the chart analysis. | F75: UI | G75: TODO
A76: F. Material groups
A77: F1 | B77: Material groups | C77: Save group from analysis | D77: Save a group (e.g. 'top 10 movers 04-26→06-26'). | E77: The group appears in the dropdown above the table. | F77: UI | G77: TODO
A78: F2 | B78: Material groups | C78: Save a second group | D78: Save a second, different group. | E78: Both groups are in the dropdown; selectable separately. | F78: UI | G78: TODO
A79: F3 | B79: Material groups | C79: Combine with line-type filter | D79: Select a group and then filter on line types. | E79: Both filters work together; only the chosen lines of the group materials. | F79: UI | G79: TODO
A80: F4 | B80: Material groups | C80: Back to 'All groups' (bug check) | D80: Choose 'All groups' in the dropdown again. | E80: ALL rows come back; you are not stuck in the group view. | F80: UI | G80: TODO
A81: F5 | B81: Material groups | C81: Switch between two groups | D81: Switch directly from group 1 to group 2. | E81: The table immediately shows the materials of group 2, no mix. | F81: UI | G81: TODO
A82: F6 | B82: Material groups | C82: Make active (scoping) | D82: Activate a group. | E82: Banner visible; dashboard shows the group's contribution margin; machines show the group hours; dropdown shows '· active'. | F82: UI | G82: TODO
A83: F7 | B83: Material groups | C83: Contribution margin correct | D83: Check the scoped financial numbers. | E83: Contribution margin = revenue − raw material − machine cost; fixed costs / EBIT / ROCE deliberately omitted. | F83: GT-D | G83: TODO
A84: F8 | B84: Material groups | C84: FTE / capacity stay plant-wide | D84: Look at FTE and capacity under an active group. | E84: They stay plant-wide (fairness rule); only revenue/cost/volume are scoped. | F84: UI | G84: TODO
A85: F9 | B85: Material groups | C85: Analysis under active group | D85: Run a chart analysis with the group active. | E85: Scoped labels known; contributions reconcile to the scoped total. | F85: UI | G85: TODO
A86: F10 | B86: Material groups | C86: Group belongs to the instance | D86: With an active group switch to the other instance and back. | E86: The other instance does not know the group and is unscoped; back, the group is still active. | F86: UI | G86: TODO
A87: F11 | B87: Material groups | C87: Active group survives restart | D87: Restart the app with a group active. | E87: After warm-up the group is still active (banner + scoped numbers). | F87: UI | G87: TODO
A88: F12 | B88: Material groups | C88: Empty intersection | D88: With an active group filter on a line type without group material. | E88: Clean explanation + button 'Restore filters'; no silent empty table. | F88: UI | G88: TODO
... A98: F22 | B98: Material groups | C98: Group with one material | D98: Make a group with exactly one material and activate it. | E98: Scoping works correctly on that one material (no division by zero in the margin). | F98: UI | G98: TODO
A99: G. Machines & capacity
A100: G1 | B100: Machines & capacity | C100: Adjust OEE | D100: Change the OEE of one machine. | E100: Automatic recalculation; utilization in table AND chart consistent. | F100: GT-B K4 | G100: TODO
A101: G2 | B101: Machines & capacity | C101: Target throughput (reverse OEE) | D101: Use the direct throughput adjustment. | E101: The OEE is adjusted proportionally to reach the target throughput; recalculation follows. | F101: GT-B K4 | G101: TODO
A102: G3 | B102: Machines & capacity | C102: Machine drill to products | D102: Click through on a machine. | E102: You see which products run hours; the sum equals the machine total. | F102: GT-D I7 | G102: TODO
A103: G4 | B103: Machines & capacity | C103: Undo OEE override | D103: Undo the OEE change (undo/reset). | E103: Utilization and FTE exactly back to the old values. | F103: GT-E | G103: TODO
A104: G5 | B104: Machines & capacity | C104: FTE follows capacity | D104: Compare FTE lines before/after a strong capacity change. | E104: The FTE requirement moves logically with the hours run. | F104: GT-B K4 | G104: TODO
A105: G6 | B105: Machines & capacity | C105: Capacity override persistent | D105: Change a capacity cell (L07/L09/L11/L12) and restart the app. | E105: The override is still there after the restart and the numbers are right. | F105: GT-E | G105: TODO
A106: G7 | B106: Machines & capacity | C106: Edge: OEE = 0 | D106: Set the OEE of a machine to 0. | E106: Clean handling (machine effectively out of use or clear message), no division by zero. | F106: UI | G106: TODO
A107: G8 | B107: Machines & capacity | C107: Edge: unlimited-capacity machine | D107: Check a machine from the 'unlimited capacity' list. | E107: It is never shown as bottleneck; utilization capped at 100 % available. | F107: UI | G107: TODO
A108: G9 | B108: Machines & capacity | C108: Utilization above 100 % | D108: Raise demand so that a machine is overloaded. | E108: The chart clearly shows the overload (> 100 %) instead of silently capping. | F108: UI | G108: TODO
A109: G10 | B109: Machines & capacity | C109: Machine × group scoping | D109: Look at machine hours under an active material group. | E109: The machine chart shows the hours of the group materials. | F109: UI | G109: TODO
A110: G11 | B110: Machines & capacity | C110: Adjust availability | D110: Change the availability (%) of a machine. | E110: Capacity per period scales along; utilization recalculated. | F110: GT-B K4 | G110: TODO
A111: G12 | B111: Machines & capacity | C111: Adjust shift hours | D111: Change the shift hours per month of a machine. | E111: Available hours and utilization move consistently. | F111: GT-B K4 | G111: TODO
... A113: G14 | B113: Machines & capacity | C113: Several machine edits + reset | D113: Make three machine edits and click reset. | E113: All machines exactly back to baseline. | F113: GT-E | G113: TODO
A114: H. Exports
A115: H1 | B115: Exports | C115: Planning export (structure + values) | D115: Export the planning workbook and open it. | E115: Opens without repair message; structure right; sample of 3 cells = exactly the UI values. Run ground_truth_diff against the GT-A. | F115: GT-A | G115: TODO
A116: H2 | B116: Exports | C116: Export contains the edits | D116: Make a recognisable edit and export again. | E116: The exported cell shows the edited value, not the original. | F116: GT-C M12 | G116: TODO
A117: H3 | B117: Exports | C117: Export contains added products | D117: Export with an added product in the session. | E117: The product is in the export with all its lines. | F117: UI | G117: TODO
...

Sheet Engine Checks
A1: Engine & pipeline checks (119 items — original verification matrix, English edition)
A2: Run per configuration: Test 1 baseline 2025-12 (12 FC / 12 actuals) · Test 2 mid-year (12 / 6) · Test 3 baseline next year · Test 4 longer forecast. Copy this sheet per configuration.
A4: # | B4: Section | C4: Check item | D4: Input / how to verify | E4: Expected | F4: Status | G4: Notes | H4: Tester | I4: Date
A5: 1. Raw Excel input / sheet validation
A6: 1 | B6: 1. Raw Excel input / sheet validation | C6: Required sheets present: Config, FTE sheet, Material master, BOM, OEE + Machine groups, Routing, Forecast sheet, Stock level sheet, Safety stock, Purchase sheet | F6: TODO
A7: 2 | B7: 1. Raw Excel input / sheet validation | C7: Optional sheets (Average sales price, Cost raw material, Cost machine hour, Valuation parameters) — no crash when missing | F7: TODO
A8: 3 | B8: 1. Raw Excel input / sheet validation | C8: Workbook opens correctly via pd.ExcelFile(file_path) | F8: TODO
A9: 4 | B9: 1. Raw Excel input / sheet validation | C9: Empty rows / missing material numbers are skipped without error | F9: TODO
A10: 2. Config sheet
A11: 5 | B11: 2. Config sheet | C11: ForecastMonths parsed correctly | F11: TODO
A12: 6 | B12: 2. Config sheet | C12: ForecastActualsMonths parsed correctly | F12: TODO
A13: 7 | B13: 2. Config sheet | C13: Site parsed correctly and used for BOM filtering | F13: TODO
A14: 8 | B14: 2. Config sheet | C14: MachineUnlimitedCapacity list read correctly | F14: TODO
A15: 9 | B15: 2. Config sheet | C15: PurchasedAndProducedMaterials MAT:ratio pairs parsed correctly | F15: TODO
A16: 10 | B16: 2. Config sheet | C16: initial_date matches the Config header date | F16: TODO
A17: 11 | B17: 2. Config sheet | C17: self.periods matches the generated planning periods | F17: TODO
A18: 12 | B18: 2. Config sheet | C18: planning_month / months_actuals / months_forecast CLI override works | F18: TODO
A19: 3. FTE sheet
A20: 13 | B20: 3. FTE sheet | C20: FTE hours per year loaded correctly | F20: TODO
A21: 14 | B21: 3. FTE sheet | C21: 2-shift, 3-shift, 24/7 hours converted to monthly values | F21: TODO
A22: 15 | B22: 3. FTE sheet | C22: Default shift name chosen from the second shift entry | F22: TODO
A23: 16 | B23: 3. FTE sheet | C23: Missing values fall back to the 3-shift system | F23: TODO
A24: 4. Material master
A25: 17 | B25: 4. Material master | C25: All material rows loaded | F25: TODO
A26: 18 | B26: 4. Material master | C26: Material number (SKU) parsed and trimmed | F26: TODO
A27: 19 | B27: 4. Material master | C27: Product type mapping works correctly | F27: TODO
A28: 20 | B28: 4. Material master | C28: Active/inactive flag parsed correctly | F28: TODO
A29: 21 | B29: 4. Material master | C29: Numeric fields (FTE requirements, Ton per truck, etc.) read safely | F29: TODO
A30: 5. BOM
A31: 22 | B31: 5. BOM | C31: Parent/component rows loaded | F31: TODO
A32: 23 | B32: 5. BOM | C32: Rows with missing parent/component skipped | F32: TODO
A33: 24 | B33: 5. BOM | C33: BOM filtered on site | F33: TODO
A34: 25 | B34: 5. BOM | C34: Zero or empty quantity skipped | F34: TODO
A35: 26 | B35: 5. BOM | C35: BOM header quantity 0 → defaults to 1 | F35: TODO
A36: 27 | B36: 5. BOM | C36: quantity_per = BILLOFMATERIALITEMQUANTITY / BOM Header Quantity | F36: TODO
A37: 28 | B37: 5. BOM | C37: Negative BOM quantities recognised as co-products | F37: TODO
A38: 29 | B38: 5. BOM | C38: BOM explosion: Child_Demand = Parent_Demand × BOM_Quantity_Per | F38: TODO
A39: 30 | B39: 5. BOM | C39: bom_levels calculation and highest BOM level count correct | F39: TODO
A40: 6. OEE + Machine groups
A41: 31 | B41: 6. OEE + Machine groups | C41: OEE + Machine groups sheet: machines loaded | F41: TODO
A42: 32 | B42: 6. OEE + Machine groups | C42: Machine groups read correctly | F42: TODO
A43: 33 | B43: 6. OEE + Machine groups | C43: Period columns match the planning periods | F43: TODO
A44: 7. Routing
A45: 34 | B45: 7. Routing | C45: Routing rows loaded | F45: TODO
A46: 35 | B46: 7. Routing | C46: Unmatched work centers → warning, no crash | F46: TODO
A47: 36 | B47: 7. Routing | C47: Machine-code matching between routing and OEE correct | F47: TODO
A48: 8. Forecast sheet
A49: 37 | B49: 8. Forecast sheet | C49: Material rows loaded | F49: TODO
A50: 38 | B50: 8. Forecast sheet | C50: First forecast period anchored correctly | F50: TODO
A51: 39 | B51: 8. Forecast sheet | C51: Actuals and forecast periods mapped correctly to internal periods | F51: TODO
A52: 40 | B52: 8. Forecast sheet | C52: months_actuals and months_forecast processed correctly | F52: TODO
A53: 9. Stock level sheet
A54: 41 | B54: 9. Stock level sheet | C54: Stock level per material loaded | F54: TODO
A55: 42 | B55: 9. Stock level sheet | C55: Starting stock values mapped correctly | F55: TODO
A56: 10. Safety stock
A57: 43 | B57: 10. Safety stock | C57: Safety stock rows loaded | F57: TODO
A58: 44 | B58: 10. Safety stock | C58: Both 'Final stafety stock' and 'Final safety stock' field names accepted | F58: TODO
A59: 45 | B59: 10. Safety stock | C59: Default target stock values loaded | F59: TODO
A60: 46 | B60: 10. Safety stock | C60: Safety-stock logic applied in the production plan | F60: TODO
A61: 11. Purchase sheet
A62: 47 | B62: 11. Purchase sheet | C62: Lead time values loaded per material | F62: TODO
A63: 48 | B63: 11. Purchase sheet | C63: MOQ values loaded | F63: TODO
A64: 49 | B64: 11. Purchase sheet | C64: Purchase material list filled | F64: TODO
A65: 50 | B65: 11. Purchase sheet | C65: Date columns parsed from the row-1 header | F65: TODO
A66: 51 | B66: 11. Purchase sheet | C66: Material actuals read from rows 8+ | F66: TODO
A67: 52 | B67: 11. Purchase sheet | C67: get_purchase_moq(material) returns 1 for a missing material | F67: TODO
A68: 53 | B68: 11. Purchase sheet | C68: Purchased-and-produced materials handled separately | F68: TODO
A69: 12. Financial sheets
A70: 54 | B70: 12. Financial sheets | C70: Average sales price sheet read (when present) | F70: TODO
A71: 55 | B71: 12. Financial sheets | C71: Cost raw material sheet read (when present) | F71: TODO
A72: 56 | B72: 12. Financial sheets | C72: Cost machine hour sheet read (when present) | F72: TODO
A73: 57 | B73: 12. Financial sheets | C73: Valuation parameters sheet read (when present) | F73: TODO
A74: 58 | B74: 12. Financial sheets | C74: Missing financial sheets do not break the raw data load | F74: TODO
A75: 13. Planning lines L01–L12
A76: 59 | B76: 13. Planning lines L01–L12 | C76: L01 Demand forecast: correct forecast values per period | F76: TODO
A77: 60 | B77: 13. Planning lines L01–L12 | C77: L01 AUX1 = average actuals | F77: TODO
A78: 61 | B78: 13. Planning lines L01–L12 | C78: L01 AUX2 = average forecast | F78: TODO
A79: 62 | B79: 13. Planning lines L01–L12 | C79: L02 Dependent demand: child demand via BOM explosion correct | F79: TODO
A80: 63 | B80: 13. Planning lines L01–L12 | C80: L03 Total demand = L01 + Σ(L02) per material × period | F80: TODO
A81: 64 | B81: 13. Planning lines L01–L12 | C81: L04 Inventory: starting stock loaded, running balance correct | F81: TODO
A82: 65 | B82: 13. Planning lines L01–L12 | C82: L05 Minimum target stock: values and AUX1 output correct | F82: TODO
A83: 66 | B83: 13. Planning lines L01–L12 | C83: L06 Production plan: ceil((Target − (Stock − Demand)) / LotSize) × LotSize | F83: TODO
A84: 67 | B84: 13. Planning lines L01–L12 | C84: L06 Production plan = 0 when stock suffices | F84: TODO
A85: 68 | B85: 13. Planning lines L01–L12 | C85: L06 Purchase receipt: MOQ and lead times correct | F85: TODO
A86: 69 | B86: 13. Planning lines L01–L12 | C86: L06 Purchase receipt: only for purchased materials | F86: TODO
A87: 70 | B87: 13. Planning lines L01–L12 | C87: L06 Purchased + produced: residual logic correct | F87: TODO
... A94: 77 | B94: 13. Planning lines L01–L12 | C94: L12 FTE requirements = Total_Hours / (FTE_Hours / 12) | F94: TODO
A95: 14. Export
A96: 78 | B96: 14. Export | C96: engine.to_dataframe() returns all expected rows | F96: TODO
A97: 79 | B97: 14. Export | C97: Period columns in YYYY-MM format | F97: TODO
A98: 80 | B98: 14. Export | C98: engine.to_excel_with_values() creates a correct xlsx file | F98: TODO
A99: 81 | B99: 14. Export | C99: Previous cycle sheet included when supplied | F99: TODO
A100: 82 | B100: 14. Export | C100: DatabaseExporter.export_to_dataframe() returns a DB-ready flat table | F100: TODO
A101: 83 | B101: 14. Export | C101: DatabaseExporter.export_to_excel(writer) writes the sheet correctly | F101: TODO
A102: 15. Cycle management & MoM
A103: 84 | B103: 15. Cycle management & MoM | C103: CycleManager.load_previous_cycle() returns the previous snapshot | F103: TODO
A104: 85 | B104: 15. Cycle management & MoM | C104: CycleManager.save_current_as_previous() stores the result | F104: TODO
A105: 86 | B105: 15. Cycle management & MoM | C105: MoMComparisonEngine.calculate() returns delta rows on overlap | F105: TODO
A106: 87 | B106: 15. Cycle management & MoM | C106: MoMComparisonEngine.create_scatter_data() returns the scatter payload | F106: TODO
A107: 16. Shutdown / restart
...

Sheet Scenario Sessions
A1: Scenario sessions — Session A: volume change → recalculation → consolidation & isolation · Session B: two files sequentially in one session
A2: Session A: Run A1 original data → Run A2 adjusted volumes in the Forecast sheet. Session B: Run B1 (2024-06, FC 12) → Run B2 (2025-01, FC 12) without restarting the app.
A4: # | B4: Session / section | C4: Check item | D4: Input | E4: Expected | F4: Status | G4: Notes | H4: Tester | I4: Date
A5: Session A — A. Input change: volume adjustment
A6: 1 | B6: Session A — A. Input change: volume adjustment | C6: Forecast sheet: volumes for ≥ 3 materials changed manually (increased AND decreased) | F6: TODO
A7: 2 | B7: Session A — A. Input change: volume adjustment | C7: Modified Excel reloaded — no parse errors | F7: TODO
A8: 3 | B8: Session A — A. Input change: volume adjustment | C8: Config sheet NOT changed — parameters identical to Run 1 | F8: TODO
A9: 4 | B9: Session A — A. Input change: volume adjustment | C9: Changed materials correctly recognised in data_loader | F9: TODO
A10: Session A — B. Recalculation after volume change
A11: 5 | B11: Session A — B. Recalculation after volume change | C11: L01 Demand forecast: changed volumes taken over correctly | F11: TODO
A12: 6 | B12: Session A — B. Recalculation after volume change | C12: L01 AUX1/AUX2 recalculated on the new values | F12: TODO
A13: 7 | B13: Session A — B. Recalculation after volume change | C13: L02 Dependent demand: BOM explosion recalculated with new parent demand | F13: TODO
A14: 8 | B14: Session A — B. Recalculation after volume change | C14: L03 Total demand: sum matches new L01 + L02 | F14: TODO
A15: 9 | B15: Session A — B. Recalculation after volume change | C15: L04 Inventory: running balance correct with new demand | F15: TODO
A16: 10 | B16: Session A — B. Recalculation after volume change | C16: L05 Minimum target stock: UNCHANGED (input not changed) | F16: TODO
A17: 11 | B17: Session A — B. Recalculation after volume change | C17: L06 Production plan: recalculated — lot-size logic correct with new demand | F17: TODO
A18: 12 | B18: Session A — B. Recalculation after volume change | C18: L06 Purchase receipt: recalculated for purchased materials | F18: TODO
A19: 13 | B19: Session A — B. Recalculation after volume change | C19: L07 Purchase plan: lead-time shift correct with new receipts | F19: TODO
A20: 14 | B20: Session A — B. Recalculation after volume change | C20: L07 Capacity utilization: recalculated with new production quantities | F20: TODO
A21: 15 | B21: Session A — B. Recalculation after volume change | C21: L08 Dependent requirements: recalculated via BOM | F21: TODO
A22: 16 | B22: Session A — B. Recalculation after volume change | C22: L09 Available capacity: UNCHANGED (no OEE/shift change) | F22: TODO
... A25: 19 | B25: Session A — B. Recalculation after volume change | C25: L12 FTE requirements: recalculated with new production quantities | F25: TODO
A26: Session A — C. Consolidation validation after change
A27: 20 | B27: Session A — C. Consolidation validation after change | C27: Total volume L03 per period = sum of all material demands | F27: TODO
A28: 21 | B28: Session A — C. Consolidation validation after change | C28: Total production L06 per period = sum of all material production plans | F28: TODO
A29: 22 | B29: Session A — C. Consolidation validation after change | C29: Total purchase L07 per period = sum of all purchase plans | F29: TODO
A30: 23 | B30: Session A — C. Consolidation validation after change | C30: Capacity utilization consolidation per machine group correct | F30: TODO
A31: 24 | B31: Session A — C. Consolidation validation after change | C31: FTE consolidation matches the sum of individual material FTE | F31: TODO
A32: 25 | B32: Session A — C. Consolidation validation after change | C32: Consolidation delta vs. Run 1 explainable from the volume changes | F32: TODO
A33: 26 | B33: Session A — C. Consolidation validation after change | C33: No unexpected changes in materials that were NOT changed | F33: TODO
A34: Session A — D. Isolation: unchanged data intact
A35: 27 | B35: Session A — D. Isolation: unchanged data intact | C35: Material master: identical to Run 1 | F35: TODO
A36: 28 | B36: Session A — D. Isolation: unchanged data intact | C36: BOM structure: identical to Run 1 | F36: TODO
A37: 29 | B37: Session A — D. Isolation: unchanged data intact | C37: OEE + Machine groups: identical to Run 1 | F37: TODO
A38: 30 | B38: Session A — D. Isolation: unchanged data intact | C38: Routing: identical to Run 1 | F38: TODO
A39: 31 | B39: Session A — D. Isolation: unchanged data intact | C39: Stock level sheet: starting stocks identical to Run 1 | F39: TODO
A40: 32 | B40: Session A — D. Isolation: unchanged data intact | C40: Safety stock: values identical to Run 1 | F40: TODO
A41: 33 | B41: Session A — D. Isolation: unchanged data intact | C41: Purchase sheet (lead times, MOQ): identical to Run 1 | F41: TODO
A42: 34 | B42: Session A — D. Isolation: unchanged data intact | C42: FTE sheet: shift configuration identical to Run 1 | F42: TODO
A43: 35 | B43: Session A — D. Isolation: unchanged data intact | C43: Financial sheets: identical to Run 1 (when present) | F43: TODO
A44: 36 | B44: Session A — D. Isolation: unchanged data intact | C44: Unchanged materials: L01–L12 output EXACTLY equal to Run 1 (ground_truth_diff Run1 vs Run2, filtered) | F44: TODO
A45: Session A — E. Export & cycle after change
A46: 37 | B46: Session A — E. Export & cycle after change | C46: Excel export contains the correct recalculated values | F46: TODO
A47: 38 | B47: Session A — E. Export & cycle after change | C47: DB export contains the correct recalculated values | F47: TODO
A48: 39 | B48: Session A — E. Export & cycle after change | C48: CycleManager: Run 1 stored as previous cycle | F48: TODO
A49: 40 | B49: Session A — E. Export & cycle after change | C49: MoM comparison: deltas match the applied volume changes | F49: TODO
A50: 41 | B50: Session A — E. Export & cycle after change | C50: MoM scatter data: only changed materials show a shift | F50: TODO
A51: Session B — F. Two consecutive files in one session
A52: 42 | B52: Session B — F. Two consecutive files in one session | C52: File 1 (Run B1) loaded and calculated — results correct | F52: TODO
A53: 43 | B53: Session B — F. Two consecutive files in one session | C53: File 2 (Run B2) loaded in the SAME session — no remains of File 1 | F53: TODO
A54: 44 | B54: Session B — F. Two consecutive files in one session | C54: All data_loader fields fully overwritten with File 2 data | F54: TODO
A55: 45 | B55: Session B — F. Two consecutive files in one session | C55: No materials from File 1 present in File 2 output | F55: TODO
A56: 46 | B56: Session B — F. Two consecutive files in one session | C56: Periods regenerated correctly for File 2 config | F56: TODO
A57: Session B — G. Result isolation between files
A58: 47 | B58: Session B — G. Result isolation between files | C58: L01–L12 output File 2: fully independent of File 1 | F58: TODO
A59: 48 | B59: Session B — G. Result isolation between files | C59: Consolidations File 2: based on File 2 data only | F59: TODO
A60: 49 | B60: Session B — G. Result isolation between files | C60: Export Excel File 2: contains NO data of File 1 | F60: TODO
A61: 50 | B61: Session B — G. Result isolation between files | C61: Export DB File 2: contains NO records of File 1 | F61: TODO
A62: 51 | B62: Session B — G. Result isolation between files | C62: Memory/state: no variables or caches of File 1 active | F62: TODO
A63: Session B — H. Cycle management over several files
A64: 52 | B64: Session B — H. Cycle management over several files | C64: CycleManager: File 1 result stored as previous cycle | F64: TODO
A65: 53 | B65: Session B — H. Cycle management over several files | C65: CycleManager: after loading File 2 the previous cycle is still File 1 | F65: TODO
A66: 54 | B66: Session B — H. Cycle management over several files | C66: MoM comparison: compares File 2 (current) vs. File 1 (previous) | F66: TODO
A67: 55 | B67: Session B — H. Cycle management over several files | C67: MoM deltas: realistic given the two different input files | F67: TODO
A68: 56 | B68: Session B — H. Cycle management over several files | C68: Scatter data: shows the comparison between both files | F68: TODO
A69: Session B — I. Session stability
A70: 57 | B70: Session B — I. Session stability | C70: No memory leaks after 2 consecutive calculations | F70: TODO
A71: 58 | B71: Session B — I. Session stability | C71: UI responsive after the second calculation | F71: TODO
A72: 59 | B72: Session B — I. Session stability | C72: Export links for BOTH runs available (or correctly overwritten) | F72: TODO
A73: 60 | B73: Session B — I. Session stability | C73: Error messages / warnings separated per run — no mixing | F73: TODO
A74: 61 | B74: Session B — I. Session stability | C74: Close the app after 2 runs — clean shutdown, no data corruption | F74: TODO

Sheet Human Tests A-K
A1: Human verification tests A–K (step-based, original 10-DOF cross-feature tests + F, G, H, I, K)
A2: A+B and C+D run in parallel with two testers; E, F, G, H, I, K solo. Each step: perform the action, tick every checkpoint, note observed values. Material numbers refer to the golden fixture (NLX1, 2025-12).
A4: Test | B4: Step | C4: Tab / tester | D4: Action (input) | E4: Verify checkpoints (expected) | F4: Observed value(s) | G4: Status | H4: Notes | I4: Screenshot / evidence
A5: TEST A+B — Parallel — Tester 1: Machines tab · Tester 2: Planning tab
A6: A+B | B6: 1 | C6: T1 Machines / T2 Planning | D6: T1: Edit PBA11 OEE: lower by 10 %. T2: Edit demand forecast for high-volume bulk material 600007751 P1: increase by 30 % (m12 → 2k, m3 → 3k). | E6: Machines: PBA11 util % increased, group row updated · Planning: L06 production plan recalculated for that material · Dashboard: utilisation chart reflects BOTH changes | G6: TODO
A7: A+B | B7: 2 | C7: T1 Machines / T2 Planning | D7: T1: Edit PM06 availability: set to 80 % uniform. T2: Edit MTS (L05) for the same material P1: set to 500. | E7: Machines: PBA12 util spikes (lower avail = higher util) · Planning: L06 increased to cover stock build + demand · Machines: machine with that material's routing shows changed req hours | G7: TODO
A8: A+B | B8: 3 | C8: T1 Machines / T2 Planning | D8: T1: Click Undo and Redo on Machines tab (PBA12 avail reverts). T2: Edit demand forecast for a 2nd material group P2 (600010763, 600008696, 600010663): decrease by 50 % until month 5. | E8: PBA12 availability back to original (per period) · Planning: L06 for 2nd material drops · Machines: machine for 2nd material shows lower util in P2 | G8: TODO
A9: A+B | B9: 4 | C9: T1 Machines / T2 Planning | D9: T1: Edit PML01 OEE: decrease by 15 %. T2: Edit product price (value aux) for material 1: change to 60 EUR. | E9: PML01 util rises · Value planning: revenue row for material 1 changes · Machines: utilisation UNCHANGED by price edit (isolation check) | G9: TODO
A10: A+B | B10: 5 | C10: T1 Machines / T2 Planning | D10: T1: Edit PBA21 availability: set to 65 %. T2: Click Volume Undo on Planning tab (reverts last demand change). | E10: PBA21 util increases · Planning: 2nd material demand back to original · Machines: machine for 2nd material util back to pre-step-3 value | G10: TODO
A11: A+B | B11: 6 | C11: T1 Machines / T2 Planning | D11: T1: Click Undo on Machines tab (PBA21 avail reverts). T2: Edit MTS for a 3rd material P3 (600013550): set to 300. | E11: PBA21 availability restored · Planning: L06 for 3rd material P3 shows production increase · Machines: routing machine for 3rd material shows higher req hours P3 | G11: TODO
A12: A+B | B12: 7 | C12: T1 Machines / T2 Planning | D12: T1: Edit PPM14 OEE: set to 35 % (extreme low). T2: Edit demand forecast for material 1 P3: increase by 100 % (600013550, 600011097, 600010878). | E12: PPM14 util very high (potentially > 100 %) · Heatmap: PBA11 row P1–P3 all red · Planning: L06 for material 1 P3 reflects doubled demand | G12: TODO
A13: A+B | B13: 8 | C13: T1 Machines / T2 Planning | D13: T1: Edit PML01 availability: back to 50 %. T2: Click Volume Undo (reverts material 1 P3 demand). | E13: PML01 util spikes (half availability) · Material 1 P3 demand back to step-7 pre-edit value · FTE requirements table: group with PML01 shows higher FTE | G13: TODO
A14: A+B | B14: 9 | C14: T1 Machines / T2 Planning | D14: T1: Click Reset on Machines tab. T2: Edit demand forecast for material 3 P1: decrease by 40 %. | E14: ALL machine OEE/availability back to original · All machine utils recalculated with original params · Planning demand edits STILL present (reset only affects machines) · Planning: material 3 shows lower L06 | G14: TODO
A15: A+B | B15: 10 | C15: both | D15: T1: Verify Undo disabled after reset. T2: Verify cross-tab consistency. | E15: Machines: Undo button greyed out · Dashboard KPIs match Machines tab values · Planning L07/L08/L09/L10/L12 match Machines tab columns · FTE totals on Machines tab match Planning L12 sums | G15: TODO
A16: TEST C+D — Parallel — Tester 1: Charts / Heatmap · Tester 2: Edits
A17: C+D | B17: 1 | C17: T1 Charts / T2 Edits | D17: T1: Open utilisation chart (slot 1), note PBA group line position. T2: Edit PBA11 OEE: lower to 1 %. | E17: Chart line for PBA group moves UP immediately · Heatmap: PBA11 cells change colour if crossing threshold | G17: TODO
A18: C+D | B18: 2 | C18: T1 Charts / T2 Edits | D18: T1: Change heatmap green threshold from 80 to 70. T2: Edit demand for PBA11's material P2 (600003816): increase ×10. | E18: Cells between 70–80 % turn yellow (were green) · Chart threshold lines move to 70 % green, same red · PBA11 P2 util even higher (OEE + demand change stacked) | G18: TODO
A19: C+D | B19: 3 | C19: T1 Charts / T2 Edits | D19: T1: Open FTE chart (slot 2). T2: Edit PBA11 availability: set to 55 %. | E19: FTE bar for PBA21's group gets taller · Utilisation chart: PBA21 group line rises · Heatmap: PBA21 cells likely red at 55 % avail | G19: TODO
A20: C+D | B20: 4 | C20: T1 Charts / T2 Edits | D20: T1: Change heatmap red threshold from 95 to 85. T2: Edit product price for any material: double it. | E20: More cells turn red (lower threshold) · OEE table colour squares update to match new thresholds · Charts/heatmap: NO change from price edit (isolation) | G20: TODO
A21: C+D | B21: 5 | C21: T1 Charts / T2 Edits | D21: T1: Select 'Utilisation per machine' from chart dropdown (slot 1). T2: Click Undo on Machines tab (PBA11 avail reverts). | E21: Dashboard util chart snapshot appears in slot 1 · PBA21 group: FTE and util drop back · Heatmap: PBA21 cells return to pre-step-3 colours | G21: TODO
A22: C+D | B22: 6 | C22: T1 Charts | D22: T1: Drag a group point on the utilisation chart DOWN to 60 % target. T2: watch. | E22: Live panel shows '60 %' while dragging · On release: panel shows required OEE per machine · Each machine's required OEE is mathematically correct (hand-check one: OEE_req = OEE × util / 0.60) | G22: TODO
A23: C+D | B23: 7 | C23: T1 Charts / T2 Edits | D23: T1: Click Cancel in the drag panel. T2: Edit MTS for any material P1: set to 400. | E23: Chart snaps back to pre-drag position · Table values unchanged · Planning: L06 P1 increased for that material | G23: TODO
A24: C+D | B24: 8 | C24: T1 Charts | D24: T1: Drag the same group point DOWN to 50 % target. T2: watch. | E24: Panel shows new required OEE values for 50 % target · Required OEEs are lower than step 6 | G24: TODO
A25: C+D | B25: 9 | C25: T1 Charts / T2 Edits | D25: T1: Click Apply. T2: Verify OEE table updated. | E25: OEE values in table match the panel's suggested values · Group util now ~50 % for that period · Heatmap colours update · FTE chart updates (lower capacity hours) | G25: TODO
A26: C+D | B26: 10 | C26: both | D26: T1: Reload page (F5), re-run Calculate. T2: Verify all state. | E26: Machine OEE/availability: back to original (drag edits NOT persisted) · Heatmap thresholds (70/85) STILL the custom values (localStorage) · Planning demand/MTS edits STILL present (pending_edits persisted) · Chart dropdown selections STILL the custom choices | G26: TODO
A27: TEST E — Solo — full workflow, one tester, sequential
A28: E | B28: 1 | C28: Planning | D28: Edit demand forecast for your highest-volume material 600004440: increase by 25 %. | E28: L03 total demand = new forecast + dependent demand · L06 production plan recalculated · L04 inventory reflects new balance | G28: TODO
A29: E | B29: 2 | C29: Machines | D29: Verify the machine for that material shows higher util. | E29: Req hours avg increased · Group util % increased · Heatmap cell for that machine/P1 changed colour if crossing threshold | G29: TODO
A30: E | B30: 3 | C30: Machines | D30: Edit the OEE for that same machine: lower by 15 %. | E30: Util % jumps further (lower OEE + higher demand) · Group row OEE avg decreased · FTE requirements for that group increased | G30: TODO
A31: E | B31: 4 | C31: Planning | D31: Edit MTS for a different material P2 (150000304 / 150000482): set to a value > 0. | E31: L05 P2 shows the new target · L06 P2 production increased to build stock · L04 P2 inventory ≥ target at end of period | G31: TODO
A32: E | B32: 5 | C32: Machines | D32: Check that the 2nd material's machine shows changed util in P2 (purchased material → redo with 500000935). | E32: Only P2 column changed (P1/P3 may shift due to inventory cascade) · Group totals updated · Utilisation chart line for that group moved | G32: TODO
A33: E | B33: 6 | C33: Dashboard | D33: Switch to Dashboard tab. | E33: Avg Utilisation KPI matches Machines tab · Total FTE KPI matches Machines tab FTE totals · Utilisation chart reflects all edits made so far | G33: TODO
A34: E | B34: 7 | C34: Machines | D34: Edit availability for a 3rd machine: set to 20 %. | E34: Util for that machine spikes · FTE for that group increases · If util > 95 %: heatmap cell red, chart line above red threshold | G34: TODO
A35: E | B35: 8 | C35: Machines | D35: Click Undo twice (reverts avail edit, then OEE edit from step 3). | E35: First undo: 3rd machine avail restored (per-period values) · Second undo: 1st machine OEE restored · All derived values (util, req_h, FTE) recalculate · Dashboard still matches | G35: TODO
A36: E | B36: 9 | C36: Planning | D36: Click Volume Undo (reverts MTS edit from step 4). | E36: L05 P2 back to 0 (or original target) · L06 P2 drops back · Machines: 2nd machine P2 util back to step-2 level | G36: TODO
A37: E | B37: 10 | C37: Machines | D37: Click Reset, then verify everything. | E37: All OEE/availability back to original · Undo button disabled · Planning: demand edit from step 1 STILL present · Machine for step-1 material still shows elevated util · All other machines at original utilisation · FTE totals recalculated | G37: TODO
A38: TEST F — Solo — multi-session isolation & state recovery after server restart (two separate sessions)
A39: F | B39: 1 | C39: — | D39: Start the application. Create Session 1 (upload MS_RECONC, run Calculate). Note the session ID. | E39: Session 1 visible in the session list | G39: TODO
A40: F | B40: 2 | C40: Planning (S1) | D40: In Session 1: increase the production plan of material 600004440 P1 by +500. | E40: L06 recalculated in Session 1 | G40: TODO
A41: F | B41: 3 | C41: Machines (S1) | D41: In Session 1: lower the OEE of PBA11 to 55 %. | E41: Utilization PBA11 increased in Session 1 | G41: TODO
A42: F | B42: 4 | C42: — | D42: Create Session 2 via 'save as instance'. Switch to Session 2. | E42: Session 2 loaded without error · all edits present | G42: TODO
A43: F | B43: 5 | C43: Planning (S2) | D43: Check the values for material 600004440 P1 in Session 2. | E43: L01/L06 show the ORIGINAL values after a reset of a separate session · no spill-over from the separate session | G43: TODO
A44: F | B44: 6 | C44: Export | D44: Export all screenshots and Excels; check quality. | E44: OEE at the ADJUSTED value (not 55 % from Session 1) · no numeric differences with the Excel financial consolidation | G44: TODO
A45: F | B45: 7 | C45: Machines (S2) | D45: In Session 2: lower the OEE of PM06 to 60 % (different machine than Session 1). | E45: PM06 utilization increased in Session 2 | G45: TODO
A46: F | B46: 8 | C46: — | D46: Switch back to Session 1. | E46: Session 1 active (header shows Session 1) | G46: TODO
A47: F | B47: 9 | C47: Machines (S1) | D47: Check PBA11 and PM06 in Session 1. | E47: PBA11 OEE still 55 % (persists) · PM06 OEE at the ORIGINAL value (edit was in Session 2) | G47: TODO
A48: F | B48: 10 | C48: Planning (S1) | D48: Check the demand forecast of 600004440 P1 in Session 1. | E48: L01 still shows +500 above original · L06 recalculated with combined edits (demand +500 AND OEE 55 %) | G48: TODO
A49: F | B49: 11 | C49: — | D49: STOP the server (Ctrl+C). Restart the server (python main.py). Open the application in the browser. | E49: Application starts without error · Session 1 AND Session 2 visible in the session list | G49: TODO
A50: F | B50: 12 | C50: Planning (S1) | D50: Switch to Session 1 after restart. Click Calculate if needed. | E50: Demand forecast 600004440 P1 still shows +500 · L06 recalculated correctly | G50: TODO
... A53: F | B53: 15 | C53: Machines (S1) | D53: Click Reset in Session 1. Check Session 2. | E53: Session 1: all OEE/availability back to original · Session 2: PM06 OEE STILL 60 % (reset is session-specific) | G53: TODO
A54: TEST G — Solo — value planning verification & export integrity
A55: G | B55: 1 | C55: Planning | D55: Note the CURRENT values (baseline): L01, L06, revenue and ROCE/cost total for material 600004440, periods P1–P3. | E55: Baseline noted | G55: TODO
A56: G | B56: 2 | C56: Planning | D56: Edit price (value aux) for material 600004440: set to 2× the current value. | E56: Revenue row doubled for all periods · L06 unchanged · L01 unchanged | G56: TODO
A57: G | B57: 3 | C57: Planning | D57: Increase the demand forecast of the same material P2 by +1000. | E57: L01 P2 increased · L06 P2 recalculated · revenue P2 = new volume × doubled price (combined effect) | G57: TODO
A58: G | B58: 4 | C58: Dashboard | D58: Go to Dashboard. | E58: Total revenue KPI increased (price × volume both changed) · Avg Utilisation KPI unchanged (price has no effect on capacity) · ROCE indicator reflected | G58: TODO
A59: G | B59: 5 | C59: Planning | D59: Undo the demand change (Volume Undo). | E59: L01 P2 back to original · revenue P2 = original volume × doubled price · L06 P2 back to baseline | G59: TODO
A60: G | B60: 6 | C60: Planning | D60: Check L12 (FTE / cost total) after the price change only. | E60: L12 UNCHANGED (price does not affect capacity/FTE) · Machines tab: all utilizations unchanged | G60: TODO
A61: G | B61: 7 | C61: — | D61: Export the planning (click Export, download the Excel). | E61: Export file downloads without error · file name contains the planning month | G61: TODO
A62: G | B62: 8 | C62: Excel | D62: Open the exported file; go to the revenue/value rows. | E62: Revenue for 600004440 in Excel = UI values from step 2 · L01 in Excel = original baseline (undo was done) · L06 in Excel = baseline · no empty cells or NaN in the value lines | G62: TODO
A63: G | B63: 9 | C63: Excel | D63: Check the capacity rows in the export (req hours, utilization, FTE). | E63: Req hours in Excel match the Machines tab · L12 FTE totals in Excel = Machines tab FTE column · all periods present | G63: TODO
A64: G | B64: 10 | C64: Planning | D64: Reset the price to original (or Undo). Export again. | E64: Second export: revenue back to original values · two exports side by side: only difference is the revenue row (all other rows identical) · UI and Excel in sync | G64: TODO
A65: TEST H — Solo — editable lines: cascade, reset, restart and isolation
A66: H | B66: 1 | C66: — | D66: Start the application. Create Session H1, upload the fixture, run Calculate. Note baseline values for L4 (600003806 starting stock + 2025-12 inventory), L7/L9/L10/L11/L12 for ZZZ_PACKGROUP01 / PBA11. | E66: Session loaded · baseline noted · no console errors | G66: TODO
A67: H | B67: 2 | C67: Planning | D67: Edit L4: set starting stock of 600003806 to 130.0 (was 30.0). | E67: L4 starting stock = 130.0 · L4 inventory 2025-12 rises by +100 · L7/L10/L12 unchanged | G67: TODO
A68: H | B68: 3 | C68: Planning | D68: Edit L7: set ZZZ_PACKGROUP01 capacity utilization 2025-12 to 700.0 (was 598.62). | E68: L7 = 700.0 · L10 PBA11 rises to ~28.14 % · L12 rises to ~5.63 · L9 unchanged | G68: TODO
A69: H | B69: 4 | C69: Planning | D69: Edit L9: set PBA11 / Z_MACH01 available capacity 2025-12 to 0.75 (was 1.0). | E69: L9 = 0.75 · L10 PBA11 rises to ~37.52 % · L12 UNCHANGED (5.63) | G69: TODO
A70: H | B70: 5 | C70: Planning | D70: Edit L11: set ZZZ_PACKGROUP01 shift availability 2025-12 to 400.0 (was 520.0). | E70: L11 = 400.0 · L10 PBA11 rises to ~48.78 % · L12 UNCHANGED (5.63) | G70: TODO
A71: H | B71: 6 | C71: Planning | D71: Edit L12: set ZZZ_PACKGROUP01 FTE requirements 2025-12 to 6.5 (was 5.63). | E71: L12 = 6.5 · L7/L9/L10/L11 unchanged · Values Planning direct FTE cost rises | G71: TODO
A72: H | B72: 7 | C72: Machines | D72: Open Machines tab, check heatmap and charts for PBA11. | E72: Utilization curve PBA11 peaks in 2025-12 · FTE chart ZZZ_PACKGROUP01 shows 6.5 in 2025-12 · no empty canvas | G72: TODO
A73: H | B73: 8 | C73: Values Planning | D73: Check L12 direct FTE cost 2025-12. | E73: Direct FTE cost ≈ 41,962.61 · Consolidation FTE cost ≈ 202,790.61 · other periods unchanged | G73: TODO
A74: H | B74: 9 | C74: Dashboard | D74: Go to Dashboard. | E74: FTE KPI up · utilisation KPI up · no NaN or '--' · charts show current values | G74: TODO
A75: H | B75: 10 | C75: Planning | D75: Click Reset in Session H1. | E75: All five edits gone · baseline values from step 1 are back · pending edits panel empty | G75: TODO
A76: H | B76: 11 | C76: Planning | D76: Re-enter the same five edits (steps 2–6, same order). | E76: End values identical to step 6 · replay order makes no difference | G76: TODO
A77: H | B77: 12 | C77: — | D77: Create Session H2 via 'Save as new instance' from H1. | E77: H2 loaded · all five edits visible in H2 · H2 shows identical L4/L7/L9/L11/L12 as H1 | G77: TODO
... A85: H | B85: 20 | C85: — | D85: Final check: compare the L10/L12 cascade matrix. | E85: L7 changes → L10 AND L12 react · L9 changes → only L10 reacts · L11 changes → only L10 reacts · L12 leaf edit → only Values Planning reacts · L4 starting stock → only L4 inventory reacts | G85: TODO
A86: TEST I — Solo — charts and export integrity
A87: I | B87: 1 | C87: — | D87: Start the application, use the same fixture as Test H. Run Calculate. | E87: Session loaded · Dashboard renders · no console errors | G87: TODO
A88: I | B88: 2 | C88: Dashboard | D88: Open the Inventory Quality chart. | E88: Bars drawn · understock bars (negative) BELOW the zero line (no Math.abs flip) · overstock bars ABOVE the zero line · legend shows both categories | G88: TODO
A89: I | B89: 3 | C89: Dashboard | D89: Hover over an understock month. | E89: Tooltip shows negative value or 'shortage' · colour = understock colour · matches the number in the table below the chart | G89: TODO
A90: I | B90: 4 | C90: Dashboard | D90: Hover over an overstock month. | E90: Tooltip shows positive value · colour = overstock colour · number matches the table | G90: TODO
A91: I | B91: 5 | C91: Dashboard | D91: Check the Actual stock line on the inventory chart. | E91: Data labels above every data point · labels show rounded stock value · no overlap with axis labels · starting stock (first point) categorised correctly | G91: TODO
A92: I | B92: 6 | C92: Dashboard | D92: Open the Projected Financial chart. | E92: Starting stock bar/line present before the first planning period · starting stock value matches L4 baseline · revenue curve starts after starting stock | G92: TODO
A93: I | B93: 7 | C93: Planning | D93: Edit L4 600003806 starting stock to 300.0. Go back to Dashboard. | E93: Inventory chart starting-stock point raised · Financial chart starting stock bar raised · Actual stock data label 2025-12 shows the new value (+270 vs baseline) | G93: TODO
A94: I | B94: 8 | C94: Dashboard | D94: Cache check: press Ctrl+F5 (hard reload) on Dashboard. | E94: Charts redrawn with L4 = 300 · no old (cached) curve visible · KPIs current | G94: TODO
A95: I | B95: 9 | C95: Inventory Quality | D95: Open the Inventory Quality tab fully. | E95: All materials show consistent understock/overstock classification · total row matches the sum of bars on Dashboard | G95: TODO
A96: I | B96: 10 | C96: Planning | D96: Edit L1 demand 600003806 2025-12 by +5000 (force understock). | E96: Inventory chart shows a negative bar in 2025-12 · data label on Actual stock line 2025-12 is negative or 0 · Inventory Quality tab marks this month as shortage | G96: TODO
A97: I | B97: 11 | C97: Machines | D97: Open Machines tab, check the utilization heatmap. | E97: Heatmap renders · colour scale consistent · tooltips show percentages · no empty cells where there is data | G97: TODO
A98: I | B98: 12 | C98: Machines | D98: Check the FTE chart ZZZ_PACKGROUP01. | E98: Line renders for all periods · end value matches L12 in the Planning tab | G98: TODO
... A106: I | B106: 20 | C106: — | D106: Final check: open both exports side by side. | E106: Differences only in the edited rows/charts · non-edited rows byte-identical · PNG charts in both exports render without broken images | G106: TODO
A107: TEST K — Solo — MoM verification, UI check and export
A108: K | B108: 1 | C108: — | D108: Start the application. Upload the golden fixture and run Calculate with planning month 2025-12. | E108: Session loaded · Dashboard shows data · no error toast · console clean | G108: TODO
A109: K | B109: 2 | C109: MoM | D109: Open the MoM tab. | E109: MoM tab visible · banner disappears or shows a meaningful status · no empty or broken layout | G109: TODO
A110: K | B110: 3 | C110: MoM | D110: Check the MoM KPI blocks. | E110: Materials count > 0 · Up/Down counts visible · Average delta shows a percentage · no NaN / undefined / '--' where data belongs | G110: TODO
A111: K | B111: 4 | C111: MoM | D111: Check the scatter plot. | E111: Points visible · axes show from/to periods · colours/markers readable · no empty canvas | G111: TODO
A112: K | B112: 5 | C112: MoM | D112: Check the Top Movers list. | E112: List contains materials · largest absolute deltas at the top · material names/numbers readable | G112: TODO
A113: K | B113: 6 | C113: MoM | D113: Check the detail table. | E113: Table contains material number, name, from/to periods, delta and delta % · first rows have numeric values | G113: TODO
A114: K | B114: 7 | C114: MoM | D114: Sort the detail table on delta % ascending, then descending. | E114: Order changes · highest and lowest movers swap logically · no rows disappear wrongly | G114: TODO
A115: K | B115: 8 | C115: MoM | D115: Search/filter on a material number visible in the table. | E115: Only matching rows remain · clearing the search restores all rows | G115: TODO
A116: K | B116: 9 | C116: Inventory | D116: Pick a material from the MoM detail table. Note the inventory values of two consecutive periods. | E116: Noted periods exist in Inventory · values are numeric | G116: TODO
A117: K | B117: 10 | C117: MoM | D117: Compare the same material in MoM. | E117: from value = Inventory previous period · to value = Inventory current period · delta = to − from · delta % right within rounding | G117: TODO
...

Sheet Deviation Register
A1: Deviation register (§10.3) — every FAIL from any sheet gets a row here
A2: Class A = app defect · B = ground-truth error (erratum) · C = definition difference (client decides) · D = presentation/rounding · E = alignment/timing · F = test artefact. Severity: Blocking / Major / Minor.
A4: # | B4: Round | C4: Sheet · material · line · period | D4: Ground-truth value | E4: App value | F4: Δ | G4: Class (A–F) | H4: Severity | I4: Analysis (root cause) | J4: Decision | K4: Decided by | L4: Date | M4: Status | N4: Evidence
A5: 1 | B5: Baseline 25-08 | C5: Values_Planning · 18 materials · 01. Demand forecast · all 12 periods (216 cells, BOTH pairs) | F5: =IF(AND(ISNUMBER(D5),ISNUMBER(E5)),E5-D5,"") | H5: Blocking | I5: Systematic, financial, in both pairs. Which tariff/volume does the revenue line use for these 18 materials (price source, PAP split)? | J5: Investigate first in Round 1 | M5: OPEN | N5: gt_ab.md / gt_cd.md
A6: 2 | B6: Baseline 25-08 | C6: Values_Planning · ZZZZZZ_INVENTORY VALUE · 13. Consolidation · Starting stock | D6: 5246842 | E6: 0 | F6: =IF(AND(ISNUMBER(D6),ISNUMBER(E6)),E6-D6,"") | G6: D · Presentation / rounding | H6: Major | I6: Export does not fill the starting-stock cell of the consolidation row. Is the value visible elsewhere in the app? | M6: OPEN
A7: 3 | B7: Baseline 25-08 | C7: Planning · Z_MACH20 · 10. Utilization rate · 2026-10..12 (and 09. Available capacity blank vs 1) | D7: 22.0402 | E7: 0.2204 | F7: =IF(AND(ISNUMBER(D7),ISNUMBER(E7)),E7-D7,"") | G7: D · Presentation / rounding | H7: Major | I7: Factor 100: Excel in %, app as fraction. Additionally the Excel has no availability in Oct–Dec 2026 — alignment or real gap? | J7: Fix the unit of L10 in the tolerance table; investigate Oct–Dec | M7: OPEN
A8: 4 | B8: Baseline 25-08 | C8: Planning · ZZ_GROUP03, Z_MACH14/15/16 · 07. Capacity utilization · several periods | D8: 442.5933 | E8: 442.5001 | F8: =IF(AND(ISNUMBER(D8),ISNUMBER(E8)),E8-D8,"") | G8: D · Presentation / rounding | H8: Minor | I8: 0.02–0.03 % lower in the app: precision of OEE/throughput in the source (76.45 vs 76.4499…). With which precision does the app read the OEE sheet? | M8: OPEN
A9: 5 | B9: Baseline 25-08 | C9: Planning · 400000455 ↔ 600007751 · 02/08 dependent demand · 2025-12 → 2026-01 (a+b only) | D9: 689.31 | E9: 492.84 | F9: =IF(AND(ISNUMBER(D9),ISNUMBER(E9)),E9-D9,"") | G9: E · Alignment / timing | H9: Major | I9: 196.47 moves from December to January (lead-time offset or a test edit on this pair). Check Edits Summary of the a+b export. | M9: OPEN
A10: 6 | B10: Baseline 25-08 | C10: Values_Planning · 13. Consolidation (a+b 50 cells, c+d 91 cells) | F10: =IF(AND(ISNUMBER(D10),ISNUMBER(E10)),E10-D10,"") | H10: Minor | I10: Derived from findings 1–5; disappears once those are explained. | J10: Re-run after 1–5 | M10: OPEN
A11: 7 | F11: =IF(AND(ISNUMBER(D11),ISNUMBER(E11)),E11-D11,"")
A12: 8 | F12: =IF(AND(ISNUMBER(D12),ISNUMBER(E12)),E12-D12,"")
A13: 9 | F13: =IF(AND(ISNUMBER(D13),ISNUMBER(E13)),E13-D13,"")
A14: 10 | F14: =IF(AND(ISNUMBER(D14),ISNUMBER(E14)),E14-D14,"")
A15: 11 | F15: =IF(AND(ISNUMBER(D15),ISNUMBER(E15)),E15-D15,"")
A16: 12 | F16: =IF(AND(ISNUMBER(D16),ISNUMBER(E16)),E16-D16,"")
A17: 13 | F17: =IF(AND(ISNUMBER(D17),ISNUMBER(E17)),E17-D17,"")
A18: 14 | F18: =IF(AND(ISNUMBER(D18),ISNUMBER(E18)),E18-D18,"")
A19: 15 | F19: =IF(AND(ISNUMBER(D19),ISNUMBER(E19)),E19-D19,"")
A20: 16 | F20: =IF(AND(ISNUMBER(D20),ISNUMBER(E20)),E20-D20,"")
A21: 17 | F21: =IF(AND(ISNUMBER(D21),ISNUMBER(E21)),E21-D21,"")
A22: 18 | F22: =IF(AND(ISNUMBER(D22),ISNUMBER(E22)),E22-D22,"")
... A40: 36 | F40: =IF(AND(ISNUMBER(D40),ISNUMBER(E40)),E40-D40,"")

Sheet Sign-off
B2: Sign-off (§10.4)
B3: Fill in after R7. A release is allowed only when all release criteria on the COVER are met.
B5: Version / commit
B6: Site(s)
B7: GT-ID(s)
B8: Evidence folder
B10: Step | C10: Executed | D10: Result (Δ=0 / findings: …) | E10: Remark
B11: R1 Baseline parity
B12: R2 Calculation chains K1–K5
B13: R3 Mirror edits (n = …)
B14: R4 Invariants I1–I11
B15: R5 Site editions (WSK / ANK)
B16: R6 Persistence / restart
B17: Engine checks (119)
B18: Scenario sessions A/B
B19: Human tests A–K
B20: main.py --test + pytest (GT-E)
B22: Open class-A findings (must be 0) | C22: =COUNTIFS('Deviation Register'!G:G,"A*",'Deviation Register'!M:M,"OPEN")
B23: Open class-C decisions | C23: =COUNTIFS('Deviation Register'!G:G,"C*",'Deviation Register'!M:M,"<>CLOSED")
B24: Errata (class B) | C24: =COUNTIF('Deviation Register'!G:G,"B*")
B26: Final verdict
B27: ☐ release ☐ release with decisions ☐ do not release
B29: Role | C29: Name | D29: Date | E29: Signature
B30: Validator
B31: Developer
B32: Reviewer
B33: Client (for class-C decisions)
